Workbook

Sheet Australia
A1: Impact_ID | B1: Impacts | C1: Pressures_Name | D1: Pressure_ID | E1: Pressures | F1: Impact_Pressure | G1: IP_UID | H1: IP_ID | I1: ID_Colour | J1: R | K1: G | L1: B | M1: A | N1: Code | O1: Impact_Descriptor | P1: Pressure_Descriptor | Q1: TimeO_Ev | R1: TimeL_Ev | S1: TimeM_Ev | T1: TimeD_Ev | U1: Space_Ev | V1: ModA | W1: ModB | X1: ModC | Y1: ModD | Z1: ModE | AA1: ModF | AB1: ModG | AC1: ModH | AD1: ModI | AE1: ConA | AF1: ConB | AG1: ConC | AH1: ConD | AI1: ConE | AJ1: ConF | AK1: ConG | AL1: ConH | AM1: ConI | AN1: ConJ | AO1: ConK | AP1: ConL | AQ1: ConM | AR1: ConN | AS1: ConO | AT1: ConP | AU1: LfA | AV1: LfB | AW1: Biomass_Ev | AX1: Water_persistence_Ev | AY1: CanopyC_Ev | AZ1: FireScar_ImpactEvidence | BA1: Hydroperiod_ImpactEvidence | BB1: HighTemp_ImpactEvidence | BD1: CTVc | BE1: NTVc | BF1: CAVc | BG1: NAVc | BH1: ASc | BI1: BSc | BJ1: AWc | BK1: NWc | BL1: Wc | BM1: CTVc2 | BN1: NTVc2 | BO1: CAV2 | BP1: NAVc2 | BQ1: ASc2 | BR1: BSc2 | BS1: AWc2 | BT1: NWc2 | BU1: Wc2 | BV1: Lifeform | BW1: canopycover | BX1: CANOPY HEIGHT (m) | BY1: SPATIAL DISTRIBUTION | BZ1: LfC | CA1: LfD | CB1: CovA | CC1: CovB | CD1: CovC | CE1: CovD | CF1: CovE | CG1: CovF | CH1: CovG | CI1: CovH | CJ1: CovI | CK1: CovJ | CL1: CovK | CM1: CovL | CN1: CovM | CO1: CovN | CP1: CovO | CQ1: CovP | CR1: CovQ | CS1: CovR | CT1: CovS | CU1: CovT | CV1: CovU | CW1: CovV | CX1: CovW | CY1: CovX | CZ1: Wstate | DA1: WperA | DB1: WperB | DC1: WperC | DD1: WperD | DE1: WperE | DF1: WperF | DG1: WseaA | DH1: WseaB | DI1: WseaC | DJ1: WseaD | DK1: AGB_Ev | DL1: AGBSD_Ev | DM1: IntEl_Ev | DN1: Canopycoa_Ev | DO1: ActiveFire | DP1: Burnscar | DQ1: Smoke | DR1: Turbidity | DS1: Flooding | DT1: Hydrograph | DU1: SnowExtent | DV1: Sediment | DW1: OceanAcidity | DX1: SeaSurfTemp | DY1: LandSurfTemp | DZ1: AtmosTemp | EA1: AtmosPress | EB1: Precipitation | EC1: Windspeed | ED1: LightningStrikesData | EE1: SeaSurfaceHeight | EF1: SeismicRecords | EG1: DogitalSurfaceModel | EH1: ForestInventory | EI1: WildlifeCensus | EJ1: StockRecords | EK1: ExtractionRegister | EL1: PlanningData | EM1: AgriRecords | EN1: AgrichemRecords | EO1: Pathogens | EP1: SoilQual | EQ1: TrafficData | ER1: WaterQual | ES1: WaterUsage | ET1: Check
A2: 1 | B2: Accretion | C2: sediment transport | D2: 111 | E2: Sediment transport | F2: Accretion (sediment transport) | G2: 1 | H2: =(A2*1000)+D2 -> 1111 | I2: Medium Slate Blue | J2: 205 | K2: 133 | L2: 63 | M2: 255 | N2: =G2&": ("&J2&", "&K2&", "&L2&", "&M2&", "&F2&": "&H2&")," -> 1: (205, 133, 63, 255, Accretion (sediment transport): 1111), | O2: =VLOOKUP(Australia!B2,Impacts!$A$2:$B$80,2, FALSE) -> The build-up of sediments to form land or shoaling in coastal waters or waterways. | P2: =VLOOKUP(E2,Pressures!$A$2:$B$145,2,FALSE) -> The movement of solid particles (sediment) caused by movement of the water volume within which they are contained and the force of gravity. | AA2: 216216 | AD2: 220220 | AW2: 0 | AX2: 0 | AZ2: 1 | BA2: 2 | BB2: 3 | BH2: 216216 | CZ2: 11 | DV2: 1 | ET2: =SUM(DO2:ES2) -> 1
A3: 2 | B3: Algal bloom | C3: eutrophication | D3: 36 | E3: Eutrophication | F3: Algal bloom (eutrophication) | G3: 2 | H3: =(A3*1000)+D3 -> 2036 | I3: Light Slate Gray | J3: 0 | K3: 255 | L3: 0 | M3: 255 | N3: =G3&": ("&J3&", "&K3&", "&L3&", "&M3&", "&F3&": "&H3&")," -> 2: (0, 255, 0, 255, Algal bloom (eutrophication): 2036), | O3: =VLOOKUP(Australia!B3,Impacts!$A$2:$B$80,2, FALSE) -> A sudden proliferation of algae (microscopic plants) that occurs near the surface of a body of water. | P3: =VLOOKUP(E3,Pressures!$A$2:$B$145,2,FALSE) -> A natural process that results from accumulation of nutrients in lakes or other bodies of water. | AB3: 227227 | AC3: 228228 | AD3: 220220 | AW3: 0 | AX3: 0 | AZ3: 1 | BA3: 2 | BB3: 3 | CZ3: 11 | ER3: 1 | ET3: =SUM(DO3:ES3) -> 1
A4: 2 | B4: Algal bloom | C4: high inland water temperatures | D4: 57 | E4: High inland water temperatures | F4: Algal bloom (high inland water temperatures) | G4: 3 | H4: =(A4*1000)+D4 -> 2057 | I4: Medium Orchid | J4: 173 | K4: 255 | L4: 47 | M4: 255 | N4: =G4&": ("&J4&", "&K4&", "&L4&", "&M4&", "&F4&": "&H4&")," -> 3: (173, 255, 47, 255, Algal bloom (high inland water temperatures): 2057), | O4: =VLOOKUP(Australia!B4,Impacts!$A$2:$B$80,2, FALSE) -> A sudden proliferation of algae (microscopic plants) that occurs near the surface of a body of water. | P4: =VLOOKUP(E4,Pressures!$A$2:$B$145,2,FALSE) -> Water temperatures of rivers, lakes, floodplains, reservoirs, wetlands, and inland saline systems that are warmer than usual. | AB4: 227227 | AC4: 228228 | AD4: 220220 | AW4: 0 | AX4: 0 | AZ4: 1 | BA4: 2 | BB4: 3 | CZ4: 11 | DY4: 1 | ET4: =SUM(DO4:ES4) -> 1
A5: 2 | B5: Algal bloom | C5: increased temperature | D5: 64 | E5: Increased temperature | F5: Algal bloom (increased temperature) | G5: 4 | H5: =(A5*1000)+D5 -> 2064 | I5: Light Salmon | J5: 124 | K5: 252 | L5: 0 | M5: 255 | N5: =G5&": ("&J5&", "&K5&", "&L5&", "&M5&", "&F5&": "&H5&")," -> 4: (124, 252, 0, 255, Algal bloom (increased temperature): 2064), | O5: =VLOOKUP(Australia!B5,Impacts!$A$2:$B$80,2, FALSE) -> A sudden proliferation of algae (microscopic plants) that occurs near the surface of a body of water. | P5: =VLOOKUP(E5,Pressures!$A$2:$B$145,2,FALSE) -> Increased amount of heat in a place. | AB5: 227227 | AC5: 228228 | AD5: 220220 | AW5: 0 | AX5: 0 | AZ5: 1 | BA5: 2 | BB5: 3 | CZ5: 11 | DZ5: 1 | ET5: =SUM(DO5:ES5) -> 1
A6: 3 | B6: Algal dieback | C6: decreased temperature | D6: 26 | E6: Decreased temperature | F6: Algal dieback (decreased temperature) | G6: 5 | H6: =(A6*1000)+D6 -> 3026 | I6: Dark Turquoise | J6: 210 | K6: 105 | L6: 30 | M6: 255 | N6: =G6&": ("&J6&", "&K6&", "&L6&", "&M6&", "&F6&": "&H6&")," -> 5: (210, 105, 30, 255, Algal dieback (decreased temperature): 3026), | O6: =VLOOKUP(Australia!B6,Impacts!$A$2:$B$80,2, FALSE) -> Loss of algae (microscopic plants) that occurs near the surface of a body of water. | P6: =VLOOKUP(E6,Pressures!$A$2:$B$145,2,FALSE) -> Decreased amount of heat in a place. | AB6: 227227 | AC6: 228228 | AD6: 220220 | AW6: 0 | AX6: 0 | AZ6: 1 | BA6: 2 | BB6: 3 | BD6: 111111 | BE6: 112112 | BV6: 22 | BX6: -□ | BY6: - | CZ6: 11 | DY6: 1 | DZ6: 1 | ET6: =SUM(DO6:ES6) -> 2
A7: 4 | B7: Bare soil exposure | C7: burning | D7: 11 | E7: Burning | F7: Bare soil exposure (burning) | G7: 6 | H7: =(A7*1000)+D7 -> 4011 | I7: Light Sky Blue | J7: 119 | K7: 63 | L7: 26 | M7: 255 | N7: =G7&": ("&J7&", "&K7&", "&L7&", "&M7&", "&F7&": "&H7&")," -> 6: (119, 63, 26, 255, Bare soil exposure (burning): 4011), | O7: =VLOOKUP(Australia!B7,Impacts!$A$2:$B$80,2, FALSE) -> Appearance of underlying soil following human or natural disturbance.. | P7: =VLOOKUP(E7,Pressures!$A$2:$B$145,2,FALSE) -> On fire. | AE7: 111216 | AF7: 112216 | AG7: 123216 | AH7: 124216 | AW7: 0 | AX7: 0 | AZ7: 1 | BA7: 2 | BB7: 3 | BD7: 111111 | BE7: 112112 | BV7: 11 | BX7: -□ | BY7: - | DO7: 1 | DP7: 1 | DQ7: 1 | ET7: =SUM(DO7:ES7) -> 3
A8: 4 | B8: Bare soil exposure | C8: erosion | D8: 35 | E8: Erosion | F8: Bare soil exposure (erosion) | G8: 7 | H8: =(A8*1000)+D8 -> 4035 | I8: Light Steel Blue | J8: 244 | K8: 164 | L8: 96 | M8: 255 | N8: =G8&": ("&J8&", "&K8&", "&L8&", "&M8&", "&F8&": "&H8&")," -> 7: (244, 164, 96, 255, Bare soil exposure (erosion): 4035), | O8: =VLOOKUP(Australia!B8,Impacts!$A$2:$B$80,2, FALSE) -> Appearance of underlying soil following human or natural disturbance.. | P8: =VLOOKUP(E8,Pressures!$A$2:$B$145,2,FALSE) -> Geological process in which earth materials are worn away and transported by natural forces such as wind or water. | AE8: 111216 | AF8: 112216 | AG8: 123216 | AH8: 124216 | AW8: 0 | AX8: 0 | AZ8: 1 | BA8: 2 | BB8: 3 | BD8: 111111 | BE8: 112112 | BV8: 11 | BX8: -□ | BY8: - | DS8: 1 | EC8: 1 | ET8: =SUM(DO8:ES8) -> 2
A9: 4 | B9: Bare soil exposure | C9: ploughing | D9: 91 | E9: Ploughing | F9: Bare soil exposure (ploughing) | G9: 8 | H9: =(A9*1000)+D9 -> 4091 | I9: Medium Purple | J9: 184 | K9: 134 | L9: 11 | M9: 255 | N9: =G9&": ("&J9&", "&K9&", "&L9&", "&M9&", "&F9&": "&H9&")," -> 8: (184, 134, 11, 255, Bare soil exposure (ploughing): 4091), | O9: =VLOOKUP(Australia!B9,Impacts!$A$2:$B$80,2, FALSE) -> Appearance of underlying soil following human or natural disturbance.. | P9: =VLOOKUP(E9,Pressures!$A$2:$B$145,2,FALSE) -> Making furrows in land mechanically, by breaking and turning over the soil. | AE9: 111216 | AW9: 0 | AX9: 0 | AZ9: 1 | BA9: 2 | BB9: 3 | BL9: 220220 | EM9: 1 | ET9: =SUM(DO9:ES9) -> 1
A10: 4 | B10: Bare soil exposure | C10: tillage | D10: 126 | E10: Tillage | F10: Bare soil exposure (tillage) | G10: 9 | H10: =(A10*1000)+D10 -> 4126 | I10: Pale Violet Red | J10: 169 | K10: 169 | L10: 169 | M10: 255 | N10: =G10&": ("&J10&", "&K10&", "&L10&", "&M10&", "&F10&": "&H10&")," -> 9: (169, 169, 169, 255, Bare soil exposure (tillage): 4126), | O10: =VLOOKUP(Australia!B10,Impacts!$A$2:$B$80,2, FALSE) -> Appearance of underlying soil following human or natural disturbance.. | P10: =VLOOKUP(E10,Pressures!$A$2:$B$145,2,FALSE) -> Preparation of soil for agricultural use through mechanical intervention such as digging, stirring, and overturning. | AE10: 111216 | AW10: 0 | AX10: 0 | AZ10: 1 | BA10: 2 | BB10: 3 | BL10: 220220 | EM10: 1 | ET10: =SUM(DO10:ES10) -> 1
A11: 5 | B11: Blackwater event | C11: inundation following extended drought | D11: 69 | E11: Inundation following extended drought | F11: Blackwater event (inundation following extended drought) | G11: 10 | H11: =(A11*1000)+D11 -> 5069 | I11: Light Green | J11: 61 | K11: 7 | L11: 52 | M11: 255 | N11: =G11&": ("&J11&", "&K11&", "&L11&", "&M11&", "&F11&": "&H11&")," -> 10: (61, 7, 52, 255, Blackwater event (inundation following extended drought): 5069), | O11: =VLOOKUP(Australia!B11,Impacts!$A$2:$B$80,2, FALSE) -> When organic material is inundated or washed into waterways and consumed by bacteria. | P11: =VLOOKUP(E11,Pressures!$A$2:$B$145,2,FALSE) -> Progressive submergence of land or structures through flooding and following an extended period of drought. | AB11: 227227 | AC11: 228228 | AD11: 220220 | AW11: 0 | AX11: 0 | AZ11: 1 | BA11: 2 | BB11: 3 | BL11: 220220 | CZ11: 11 | DS11: 1 | EB11: 1 | ET11: =SUM(DO11:ES11) -> 2
A12: 6 | B12: Browning (vegetation) | C12: decreased precipitation | D12: 25 | E12: Decreased precipitation | F12: Browning (vegetation) (decreased precipitation) | G12: 11 | H12: =(A12*1000)+D12 -> 6025 | I12: Medium Spring Green | J12: 255 | K12: 228 | L12: 181 | M12: 255 | N12: =G12&": ("&J12&", "&K12&", "&L12&", "&M12&", "&F12&": "&H12&")," -> 11: (255, 228, 181, 255, Browning (vegetation) (decreased precipitation): 6025), | O12: =VLOOKUP(Australia!B12,Impacts!$A$2:$B$80,2, FALSE) -> A decrease in the amount or loss of photosynthetically active pigments in vegetation. | P12: =VLOOKUP(E12,Pressures!$A$2:$B$145,2,FALSE) -> Decreased condensation of water vapour in the atmosphere forming rain, snow, sleet or dew. | V12: 111111 | W12: 112112 | X12: 123123 | Y12: 124124 | CB12: 1012 | CC12: 1013 | CD12: 1015 | CE12: 1016 | CF12: 1213 | CG12: 1215 | CH12: 1216 | CI12: 1315 | CJ12: 1316 | CK12: 1516 | EB12: 1 | ET12: =SUM(DO12:ES12) -> 1
A13: 7 | B13: Building or infrastucture abandonment | C13: dam removal | D13: 21 | E13: Dam removal | F13: Building or infrastructure abandonment (dam removal) | G13: 12 | H13: =(A13*1000)+D13 -> 7021 | I13: Light Cyan | J13: 147 | K13: 112 | L13: 219 | M13: 255 | N13: =G13&": ("&J13&", "&K13&", "&L13&", "&M13&", "&F13&": "&H13&")," -> 12: (147, 112, 219, 255, Building or infrastructure abandonment (dam removal): 7021), | O13: =VLOOKUP(Australia!B13,Impacts!$A$2:$B$80,2, FALSE) -> Buildings dehabited or no longer in use. | P13: =VLOOKUP(E13,Pressures!$A$2:$B$145,2,FALSE) -> Demolition/decommissioning of a dam enabling reinstatement of unconstrained water flow and typically reducing pooled water. | AE13: 215216 | AF13: 227216 | AG13: 220216 | AW13: 0 | AX13: 0 | AZ13: 1 | BA13: 2 | BB13: 3 | BL13: 220220 | ES13: 1 | ET13: =SUM(DO13:ES13) -> 1
A14: 7 | B14: Building or infrastucture abandonment | C14: flooding | D14: 44 | E14: Flooding | F14: Building or infrastructure abandonment (flooding) | G14: 13 | H14: =(A14*1000)+D14 -> 7044 | I14: Dark Orchid | J14: 123 | K14: 104 | L14: 238 | M14: 255 | N14: =G14&": ("&J14&", "&K14&", "&L14&", "&M14&", "&F14&": "&H14&")," -> 13: (123, 104, 238, 255, Building or infrastructure abandonment (flooding): 7044), | O14: =VLOOKUP(Australia!B14,Impacts!$A$2:$B$80,2, FALSE) -> Buildings dehabited or no longer in use. | P14: =VLOOKUP(E14,Pressures!$A$2:$B$145,2,FALSE) -> The inundation of water over land that is generally dry. | AE14: 215220 | AF14: 215227 | AG14: 215220 | AW14: 0 | AX14: 0 | AZ14: 1 | BA14: 2 | BB14: 3 | DS14: 1 | ET14: =SUM(DO14:ES14) -> 1
A15: 7 | B15: Building or infrastucture abandonment | C15: increased wind | D15: 66 | E15: Increased wind | F15: Building or infrastructure abandonment (increased wind) | G15: 14 | H15: =(A15*1000)+D15 -> 7066 | I15: Cornflower Blue | J15: 70 | K15: 130 | L15: 180 | M15: 255 | N15: =G15&": ("&J15&", "&K15&", "&L15&", "&M15&", "&F15&": "&H15&")," -> 14: (70, 130, 180, 255, Building or infrastructure abandonment (increased wind): 7066), | O15: =VLOOKUP(Australia!B15,Impacts!$A$2:$B$80,2, FALSE) -> Buildings dehabited or no longer in use. | P15: =VLOOKUP(E15,Pressures!$A$2:$B$145,2,FALSE) -> A higher velocity of air movement into an area associated with, for example, cyclones, hurricans, typhoons, tornados, thunderstorms, storms or ice storms. | Z15: 215215 | AW15: 0 | AX15: 0 | AZ15: 1 | BA15: 2 | BB15: 3 | BL15: 220220 | EC15: 1 | ET15: =SUM(DO15:ES15) -> 1
A16: 7 | B16: Building or infrastucture abandonment | C16: urban fire | D16: 131 | E16: Urban fire | F16: Building or infrastructure abandonment (urban fire) | G16: 15 | H16: =(A16*1000)+D16 -> 7131 | I16: Light Yellow | J16: 148 | K16: 0 | L16: 211 | M16: 255 | N16: =G16&": ("&J16&", "&K16&", "&L16&", "&M16&", "&F16&": "&H16&")," -> 15: (148, 0, 211, 255, Building or infrastructure abandonment (urban fire): 7131), | O16: =VLOOKUP(Australia!B16,Impacts!$A$2:$B$80,2, FALSE) -> Buildings dehabited or no longer in use. | P16: =VLOOKUP(E16,Pressures!$A$2:$B$145,2,FALSE) -> Urban fire occurs primarily in cities or towns with the potential to rapidly spread to adjoining structures. | Z16: 215215 | AE16: 215216 | AW16: 0 | AX16: 0 | AZ16: 1 | BA16: 2 | BB16: 3 | BL16: 220220 | DO16: 1 | DP16: 1 | DQ16: 1 | ET16: =SUM(DO16:ES16) -> 3
A17: 8 | B17: Compaction | C17: increased traffic | D17: 65 | E17: Increased traffic | F17: Compaction (increased traffic) | G17: 16 | H17: =(A17*1000)+D17 -> 8065 | I17: Dark Orange | J17: 218 | K17: 165 | L17: 32 | M17: 255 | N17: =G17&": ("&J17&", "&K17&", "&L17&", "&M17&", "&F17&": "&H17&")," -> 16: (218, 165, 32, 255, Compaction (increased traffic): 8065), | O17: =VLOOKUP(Australia!B17,Impacts!$A$2:$B$80,2, FALSE) -> Process that brings about an increase in soil density or unit weight. | P17: =VLOOKUP(E17,Pressures!$A$2:$B$145,2,FALSE) -> A greater number of vehicles moving along roads, or the amount of aircraft, trains, or ships moving along a route. | AA17: 216216 | AW17: 0 | AX17: 0 | AZ17: 1 | BA17: 2 | BB17: 3 | BD17: 111111 | BF17: 123123 | EQ17: 1 | ET17: =SUM(DO17:ES17) -> 1
A18: 8 | B18: Compaction | C18: overgrazing (natural) | D18: 86 | E18: Overgrazing (natural) | F18: Compaction (overgrazing (natural)) | G18: 17 | H18: =(A18*1000)+D18 -> 8086 | I18: Pale Green | J18: 240 | K18: 230 | L18: 140 | M18: 255 | N18: =G18&": ("&J18&", "&K18&", "&L18&", "&M18&", "&F18&": "&H18&")," -> 17: (240, 230, 140, 255, Compaction (overgrazing (natural)): 8086), | O18: =VLOOKUP(Australia!B18,Impacts!$A$2:$B$80,2, FALSE) -> Process that brings about an increase in soil density or unit weight. | P18: =VLOOKUP(E18,Pressures!$A$2:$B$145,2,FALSE) -> Excessive grazing by natural animal populations without sufficient rest, resulting in declines in the biomass or health of vegetation. | AA18: 216216 | AW18: -1 | AX18: 0 | AZ18: 1 | BA18: 2 | BB18: 3 | BD18: 111111 | EI18: 1 | ET18: =SUM(DO18:ES18) -> 1
A19: 8 | B19: Compaction | C19: overgrazing (stock) | D19: 87 | E19: Overgrazing (stock) | F19: Compaction (overgrazing (stock)) | G19: 18 | H19: =(A19*1000)+D19 -> 8087 | I19: Medium Aquamarine | J19: 222 | K19: 184 | L19: 135 | M19: 255 | N19: =G19&": ("&J19&", "&K19&", "&L19&", "&M19&", "&F19&": "&H19&")," -> 18: (222, 184, 135, 255, Compaction (overgrazing (stock)): 8087), | O19: =VLOOKUP(Australia!B19,Impacts!$A$2:$B$80,2, FALSE) -> Process that brings about an increase in soil density or unit weight. | P19: =VLOOKUP(E19,Pressures!$A$2:$B$145,2,FALSE) -> Excessive grazing by domesticated stock without sufficient rest, resulting in declines in the biomass or health of vegetation. | V19: 111111 | W19: 112112 | Y19: 124124 | AW19: -1 | AX19: 0 | AZ19: 1 | BA19: 2 | BB19: 3 | BD19: 111111 | CZ19: 11 | DA19: 11 | EJ19: 1 | ET19: =SUM(DO19:ES19) -> 1
A20: 9 | B20: Coral bleaching | C20: increased acidity | D20: 59 | E20: Increased acidity | F20: Coral bleaching (increased acidity) | G20: 19 | H20: =(A20*1000)+D20 -> 9059 | I20: Light Pink | J20: 250 | K20: 250 | L20: 210 | M20: 255 | N20: =G20&": ("&J20&", "&K20&", "&L20&", "&M20&", "&F20&": "&H20&")," -> 19: (250, 250, 210, 255, Coral bleaching (increased acidity): 9059), | O20: =VLOOKUP(Australia!B20,Impacts!$A$2:$B$80,2, FALSE) -> When the coral host expels its zooxanthellae. | P20: =VLOOKUP(E20,Pressures!$A$2:$B$145,2,FALSE) -> A decrease in the pH of water or soils across the range of alkaline (7-14), neutral (7) to acidic (0 to 7). | AC20: 228228 | AD20: 220220 | AW20: -1 | AX20: 0 | AZ20: 1 | BA20: 2 | BB20: 3 | BD20: 111111 | CZ20: 11 | DA20: 11 | DW20: 1 | ER20: 1 | ET20: =SUM(DO20:ES20) -> 2
A21: 9 | B21: Coral bleaching | C21: prolonged temperature increase | D21: 97 | E21: Prolonged temperature increase | F21: Coral bleaching (prolonged temperature increase) | G21: 20 | H21: =(A21*1000)+D21 -> 9097 | I21: Sea Green | J21: 250 | K21: 240 | L21: 230 | M21: 255 | N21: =G21&": ("&J21&", "&K21&", "&L21&", "&M21&", "&F21&": "&H21&")," -> 20: (250, 240, 230, 255, Coral bleaching (prolonged temperature increase): 9097), | O21: =VLOOKUP(Australia!B21,Impacts!$A$2:$B$80,2, FALSE) -> When the coral host expels its zooxanthellae. | P21: =VLOOKUP(E21,Pressures!$A$2:$B$145,2,FALSE) -> Seasonal to multi-annual increases in temperature compared with past averages. | AC21: 228228 | AD21: 220220 | AW21: -1 | AX21: 0 | AZ21: 1 | BA21: 2 | BB21: 3 | BD21: 111111 | CZ21: 11 | DA21: 11 | DX21: 1 | ET21: =SUM(DO21:ES21) -> 1
A22: 10 | B22: Coral damage | C22: invasive or exotic species | D22: 70 | E22: Invasive/exotic species | F22: Coral damage (invasive or exotic species) | G22: 21 | H22: =(A22*1000)+D22 -> 10070 | I22: Peru | J22: 199 | K22: 21 | L22: 133 | M22: 255 | N22: =G22&": ("&J22&", "&K22&", "&L22&", "&M22&", "&F22&": "&H22&")," -> 21: (199, 21, 133, 255, Coral damage (invasive or exotic species): 10070), | O22: =VLOOKUP(Australia!B22,Impacts!$A$2:$B$80,2, FALSE) -> Physical damage or loss of a coral reef not caused b y changes in water temperature | P22: =VLOOKUP(E22,Pressures!$A$2:$B$145,2,FALSE) -> A plant or animal that has been introduced into a region (terrestrial or aquatic) in which it does not naturally occur. | AC22: 228228 | AD22: 220220 | AW22: -1 | AX22: 0 | AZ22: 1 | BA22: 2 | BB22: 3 | BD22: 111111 | CZ22: 11 | DA22: 11 | EI22: 1 | EO22: 1 | ET22: =SUM(DO22:ES22) -> 2
A23: 10 | B23: Coral damage | C23: pathogens | D23: 88 | E23: Pathogens | F23: Coral damage (pathogens) | G23: 22 | H23: =(A23*1000)+D23 -> 10088 | I23: Indian Red | J23: 255 | K23: 228 | L23: 225 | M23: 255 | N23: =G23&": ("&J23&", "&K23&", "&L23&", "&M23&", "&F23&": "&H23&")," -> 22: (255, 228, 225, 255, Coral damage (pathogens): 10088), | O23: =VLOOKUP(Australia!B23,Impacts!$A$2:$B$80,2, FALSE) -> Physical damage or loss of a coral reef not caused b y changes in water temperature | P23: =VLOOKUP(E23,Pressures!$A$2:$B$145,2,FALSE) -> Any small organism, such as a virus or a bacterium that can cause disease. | AC23: 228228 | AD23: 220220 | AW23: -1 | AX23: 0 | AZ23: 1 | BA23: 2 | BB23: 3 | BD23: 111111 | CZ23: 11 | DA23: 11 | EO23: 1 | ET23: =SUM(DO23:ES23) -> 1
A24: 10 | B24: Coral damage | C24: sedimentation | D24: 112 | E24: Sedimentation | F24: Coral damage (sedimentation) | G24: 23 | H24: =(A24*1000)+D24 -> 10112 | I24: Tan | J24: 255 | K24: 222 | L24: 173 | M24: 255 | N24: =G24&": ("&J24&", "&K24&", "&L24&", "&M24&", "&F24&": "&H24&")," -> 23: (255, 222, 173, 255, Coral damage (sedimentation): 10112), | O24: =VLOOKUP(Australia!B24,Impacts!$A$2:$B$80,2, FALSE) -> Physical damage or loss of a coral reef not caused b y changes in water temperature | P24: =VLOOKUP(E24,Pressures!$A$2:$B$145,2,FALSE) -> Deposition of sediment from flowing water (in channels or floodplains) or standing water (in wetlands, lakes, or oceans). | AC24: 228228 | AD24: 220220 | AW24: -1 | AX24: 0 | AZ24: 1 | BA24: 2 | BB24: 3 | BD24: 111111 | CZ24: 11 | DA24: 11 | DV24: 1 | ET24: =SUM(DO24:ES24) -> 1
A25: 11 | B25: Coral recovery | C25: decreased acidity | D25: 22 | E25: Decreased acidity | F25: Coral recovery (decreased acidity) | G25: 24 | H25: =(A25*1000)+D25 -> 11022 | I25: Dark Khaki | J25: 248 | K25: 131 | L25: 121 | M25: 255 | N25: =G25&": ("&J25&", "&K25&", "&L25&", "&M25&", "&F25&": "&H25&")," -> 24: (248, 131, 121, 255, Coral recovery (decreased acidity): 11022), | O25: =VLOOKUP(Australia!B25,Impacts!$A$2:$B$80,2, FALSE) -> Re-instatement of the previous extent or health of reef-building corals. | P25: =VLOOKUP(E25,Pressures!$A$2:$B$145,2,FALSE) -> A increase in the pH of water or soils across the range of alkaline (7-14), neutral (7) to acidic (0 to 7). | AC25: 228228 | AD25: 220220 | AW25: -1 | AX25: 0 | AZ25: 1 | BA25: 2 | BB25: 3 | BD25: 111111 | CZ25: 11 | DA25: 11 | ER25: 1 | ET25: =SUM(DO25:ES25) -> 1
A26: 11 | B26: Coral recovery | C26: prolonged temperature decrease | D26: 96 | E26: Prolonged temperature decrease | F26: Coral recovery (prolonged temperature decrease) | G26: 25 | H26: =(A26*1000)+D26 -> 11096 | I26: Rosy Brown | J26: 255 | K26: 127 | L26: 80 | M26: 255 | N26: =G26&": ("&J26&", "&K26&", "&L26&", "&M26&", "&F26&": "&H26&")," -> 25: (255, 127, 80, 255, Coral recovery (prolonged temperature decrease): 11096), | O26: =VLOOKUP(Australia!B26,Impacts!$A$2:$B$80,2, FALSE) -> Re-instatement of the previous extent or health of reef-building corals. | P26: =VLOOKUP(E26,Pressures!$A$2:$B$145,2,FALSE) -> Seasonal to multi-annual decreases in temperature compared with past averages. | AC26: 228228 | AD26: 220220 | AW26: -1 | AX26: 0 | AZ26: 1 | BA26: 2 | BB26: 3 | BD26: 111111 | CZ26: 11 | DA26: 11 | DX26: 1 | ET26: =SUM(DO26:ES26) -> 1
A27: 12 | B27: Crop change in cultivated lands | C27: crop rotation | D27: 19 | E27: Crop rotation | F27: Crop change in cultivated lands (crop rotation) | G27: 26 | H27: =(A27*1000)+D27 -> 12019 | I27: Dark Olive Green | J27: 255 | K27: 182 | L27: 30 | M27: 255 | N27: =G27&": ("&J27&", "&K27&", "&L27&", "&M27&", "&F27&": "&H27&")," -> 26: (255, 182, 30, 255, Crop change in cultivated lands (crop rotation): 12019), | O27: =VLOOKUP(Australia!B27,Impacts!$A$2:$B$80,2, FALSE) -> Replacement of one crop type by another. | P27: =VLOOKUP(E27,Pressures!$A$2:$B$145,2,FALSE) -> Alternating between types of crops on a seasonal basis in the same area to limit soil degradation and to help control weeds, diseases and pests. | AU27: 11 | AV27: 22 | AW27: 1 | AX27: 0 | AZ27: 1 | BA27: 2 | BB27: 3 | BJ27: 216111 | BZ27: 12 | CA27: 21 | CB27: 1010 | CC27: 1212 | CD27: 1313 | CE27: 1515 | CF27: 1616 | EM27: 1 | ET27: =SUM(DO27:ES27) -> 1
A28: 13 | B28: Crop damage | C28: drought | D28: 30 | E28: Drought | F28: Crop damage (drought) | G28: 27 | H28: =(A28*1000)+D28 -> 13030 | I28: Olive Drab | J28: 184 | K28: 115 | L28: 51 | M28: 255 | N28: =G28&": ("&J28&", "&K28&", "&L28&", "&M28&", "&F28&": "&H28&")," -> 27: (184, 115, 51, 255, Crop damage (drought): 13030), | O28: =VLOOKUP(Australia!B28,Impacts!$A$2:$B$80,2, FALSE) -> Loss of or harm to crops during or following a disturbance. | P28: =VLOOKUP(E28,Pressures!$A$2:$B$145,2,FALSE) -> Areas considered to be suffering from a serious or severe rainfall deficiency. | V28: 111111 | X28: 123123 | AU28: 11 | AV28: 22 | AW28: 1 | AX28: 0 | AZ28: 1 | BA28: 2 | BB28: 3 | BE28: 112111 | BG28: 124123 | CB28: 1012 | CC28: 1013 | CD28: 1015 | CE28: 1016 | CF28: 1213 | CG28: 1215 | CH28: 1216 | CI28: 1315 | CJ28: 1316 | CK28: 1516 | EB28: 1 | ET28: =SUM(DO28:ES28) -> 1
A29: 13 | B29: Crop damage | C29: excess precipitation | D29: 38 | E29: Excess precipitation | F29: Crop damage (excess precipitation) | G29: 28 | H29: =(A29*1000)+D29 -> 13038 | I29: Slate Gray | J29: 205 | K29: 149 | L29: 117 | M29: 255 | N29: =G29&": ("&J29&", "&K29&", "&L29&", "&M29&", "&F29&": "&H29&")," -> 28: (205, 149, 117, 255, Crop damage (excess precipitation): 13038), | O29: =VLOOKUP(Australia!B29,Impacts!$A$2:$B$80,2, FALSE) -> Loss of or harm to crops during or following a disturbance. | P29: =VLOOKUP(E29,Pressures!$A$2:$B$145,2,FALSE) -> Above-normal increase in the amount of rain or snowfall. | V29: 111111 | X29: 123123 | AU29: 11 | AV29: 22 | AW29: 1 | AX29: 0 | AZ29: 1 | BA29: 2 | BB29: 3 | BE29: 112111 | BG29: 124123 | CB29: 1012 | CC29: 1013 | CD29: 1015 | CE29: 1016 | CF29: 1213 | CG29: 1215 | CH29: 1216 | CI29: 1315 | CJ29: 1316 | CK29: 1516 | EB29: 1 | ET29: =SUM(DO29:ES29) -> 1
A30: 13 | B30: Crop damage | C30: excess rain | D30: 39 | E30: Excess rain | F30: Crop damage (excess rain) | G30: 29 | H30: =(A30*1000)+D30 -> 13039 | I30: Lavender | J30: 145 | K30: 95 | L30: 109 | M30: 255 | N30: =G30&": ("&J30&", "&K30&", "&L30&", "&M30&", "&F30&": "&H30&")," -> 29: (145, 95, 109, 255, Crop damage (excess rain): 13039), | O30: =VLOOKUP(Australia!B30,Impacts!$A$2:$B$80,2, FALSE) -> Loss of or harm to crops during or following a disturbance. | P30: =VLOOKUP(E30,Pressures!$A$2:$B$145,2,FALSE) -> Heavy rainfall associated with the passage of a storm or tropical cyclone than can produce extensive flooding. | V30: 111111 | X30: 123123 | AU30: 11 | AV30: 22 | AW30: -1 | AX30: 0 | AZ30: 1 | BA30: 2 | BB30: 3 | BD30: 111112 | BF30: 123124 | CB30: 1012 | CC30: 1013 | CD30: 1015 | CE30: 1016 | CF30: 1213 | CG30: 1215 | CH30: 1216 | CI30: 1315 | CJ30: 1316 | CK30: 1516 | EB30: 1 | ET30: =SUM(DO30:ES30) -> 1
A31: 13 | B31: Crop damage | C31: flooding | D31: 44 | E31: Flooding | F31: Crop damage (flooding) | G31: 30 | H31: =(A31*1000)+D31 -> 13044 | I31: Ghost White | J31: 18 | K31: 97 | L31: 128 | M31: 255 | N31: =G31&": ("&J31&", "&K31&", "&L31&", "&M31&", "&F31&": "&H31&")," -> 30: (18, 97, 128, 255, Crop damage (flooding): 13044), | O31: =VLOOKUP(Australia!B31,Impacts!$A$2:$B$80,2, FALSE) -> Loss of or harm to crops during or following a disturbance. | P31: =VLOOKUP(E31,Pressures!$A$2:$B$145,2,FALSE) -> The inundation of water over land that is generally dry. | V31: 111111 | X31: 123123 | AU31: 11 | AV31: 22 | AW31: -1 | AX31: 0 | AZ31: 1 | BA31: 2 | BB31: 3 | BD31: 111111 | CB31: 1012 | CC31: 1013 | CD31: 1015 | CE31: 1016 | CF31: 1213 | CG31: 1215 | CH31: 1216 | CI31: 1315 | CJ31: 1316 | CK31: 1516 | DS31: 1 | ET31: =SUM(DO31:ES31) -> 1
A32: 13 | B32: Crop damage | C32: grazing (natural) | D32: 48 | E32: Grazing (natural) | F32: Crop damage (grazing (natural)) | G32: 31 | H32: =(A32*1000)+D32 -> 13048 | I32: Blue | J32: 244 | K32: 164 | L32: 96 | M32: 255 | N32: =G32&": ("&J32&", "&K32&", "&L32&", "&M32&", "&F32&": "&H32&")," -> 31: (244, 164, 96, 255, Crop damage (grazing (natural)): 13048), | O32: =VLOOKUP(Australia!B32,Impacts!$A$2:$B$80,2, FALSE) -> Loss of or harm to crops during or following a disturbance. | P32: =VLOOKUP(E32,Pressures!$A$2:$B$145,2,FALSE) -> Repetitive consumption of herbaceous or woody vegetation by herbivores/omnivores. | V32: 111111 | X32: 123123 | AU32: 11 | AV32: 22 | AW32: -1 | AX32: 0 | AZ32: 1 | BA32: 2 | BB32: 3 | BD32: 111111 | CB32: 1012 | CC32: 1013 | CD32: 1015 | CE32: 1016 | CF32: 1213 | CG32: 1215 | CH32: 1216 | CI32: 1315 | CJ32: 1316 | CK32: 1516 | EI32: 1 | ET32: =SUM(DO32:ES32) -> 1
A33: 13 | B33: Crop damage | C33: grazing (stock) | D33: 49 | E33: Grazing (stock) | F33: Crop damage (grazing (stock)) | G33: 32 | H33: =(A33*1000)+D33 -> 13049 | I33: Green | J33: 160 | K33: 82 | L33: 45 | M33: 255 | N33: =G33&": ("&J33&", "&K33&", "&L33&", "&M33&", "&F33&": "&H33&")," -> 32: (160, 82, 45, 255, Crop damage (grazing (stock)): 13049), | O33: =VLOOKUP(Australia!B33,Impacts!$A$2:$B$80,2, FALSE) -> Loss of or harm to crops during or following a disturbance. | P33: =VLOOKUP(E33,Pressures!$A$2:$B$145,2,FALSE) -> Repetitive consumption of herbaceous or woody vegetation by domesticated herbivores/omnivores. | V33: 111111 | X33: 123123 | AU33: 11 | AV33: 22 | AW33: -1 | AX33: 0 | AZ33: 1 | BA33: 2 | BB33: 3 | BE33: 111112 | CB33: 1012 | CC33: 1013 | CD33: 1015 | CE33: 1016 | CF33: 1213 | CG33: 1215 | CH33: 1216 | CI33: 1315 | CJ33: 1316 | CK33: 1516 | EJ33: 1 | ET33: =SUM(DO33:ES33) -> 1
A34: 13 | B34: Crop damage | C34: increased wind | D34: 66 | E34: Increased wind | F34: Crop damage (increased wind) | G34: 33 | H34: =(A34*1000)+D34 -> 13066 | I34: Cyan | J34: 184 | K34: 125 | L34: 73 | M34: 255 | N34: =G34&": ("&J34&", "&K34&", "&L34&", "&M34&", "&F34&": "&H34&")," -> 33: (184, 125, 73, 255, Crop damage (increased wind): 13066), | O34: =VLOOKUP(Australia!B34,Impacts!$A$2:$B$80,2, FALSE) -> Loss of or harm to crops during or following a disturbance. | P34: =VLOOKUP(E34,Pressures!$A$2:$B$145,2,FALSE) -> A higher velocity of air movement into an area associated with, for example, cyclones, hurricans, typhoons, tornados, thunderstorms, storms or ice storms. | V34: 111111 | X34: 123123 | AU34: 11 | AV34: 22 | AW34: -1 | AX34: 0 | AZ34: 1 | BA34: 2 | BB34: 3 | BD34: 111111 | CB34: 1012 | CC34: 1013 | CD34: 1015 | CE34: 1016 | CF34: 1213 | CG34: 1215 | CH34: 1216 | CI34: 1315 | CJ34: 1316 | CK34: 1516 | EC34: 1 | ET34: =SUM(DO34:ES34) -> 1
A35: 13 | B35: Crop damage | C35: insect herbivory | D35: 67 | E35: Insect herbivory | F35: Crop damage (insect herbivory) | G35: 34 | H35: =(A35*1000)+D35 -> 13067 | I35: Red | J35: 255 | K35: 218 | L35: 185 | M35: 255 | N35: =G35&": ("&J35&", "&K35&", "&L35&", "&M35&", "&F35&": "&H35&")," -> 34: (255, 218, 185, 255, Crop damage (insect herbivory): 13067), | O35: =VLOOKUP(Australia!B35,Impacts!$A$2:$B$80,2, FALSE) -> Loss of or harm to crops during or following a disturbance. | P35: =VLOOKUP(E35,Pressures!$A$2:$B$145,2,FALSE) -> Increased presence of plant-consuming insects in an area. | V35: 111111 | X35: 123123 | AU35: 11 | AV35: 22 | AW35: 1 | AX35: 0 | AZ35: 1 | BA35: 2 | BB35: 3 | BL35: 210216 | CB35: 1012 | CC35: 1013 | CD35: 1015 | CE35: 1016 | CF35: 1213 | CG35: 1215 | CH35: 1216 | CI35: 1315 | CJ35: 1316 | CK35: 1516 | EI35: 1 | EO35: 1 | ET35: =SUM(DO35:ES35) -> 2
A36: 13 | B36: Crop damage | C36: strong winds | D36: 120 | E36: Strong winds | F36: Crop damage (strong winds) | G36: 35 | H36: =(A36*1000)+D36 -> 13120 | I36: Magenta | J36: 184 | K36: 115 | L36: 51 | M36: 255 | N36: =G36&": ("&J36&", "&K36&", "&L36&", "&M36&", "&F36&": "&H36&")," -> 35: (184, 115, 51, 255, Crop damage (strong winds): 13120), | O36: =VLOOKUP(Australia!B36,Impacts!$A$2:$B$80,2, FALSE) -> Loss of or harm to crops during or following a disturbance. | P36: =VLOOKUP(E36,Pressures!$A$2:$B$145,2,FALSE) -> A prolonged period of average wind speeds exceeding 40km/h during the day. | V36: 111111 | X36: 123123 | AU36: 11 | AV36: 22 | AW36: 0 | AX36: 0 | AZ36: 1 | BA36: 2 | BB36: 3 | BD36: 111111 | CB36: 1012 | CC36: 1013 | CD36: 1015 | CE36: 1016 | CF36: 1213 | CG36: 1215 | CH36: 1216 | CI36: 1315 | CJ36: 1316 | CK36: 1516 | EC36: 1 | ED36: 1 | ET36: =SUM(DO36:ES36) -> 2
A37: 14 | B37: Crop establishment | C37: planting | D37: 90 | E37: Planting | F37: Crop establishment (planting) | G37: 36 | H37: =(A37*1000)+D37 -> 14090 | I37: Yellow | J37: 167 | K37: 252 | L37: 0 | M37: 255 | N37: =G37&": ("&J37&", "&K37&", "&L37&", "&M37&", "&F37&": "&H37&")," -> 36: (167, 252, 0, 255, Crop establishment (planting): 14090), | O37: =VLOOKUP(Australia!B37,Impacts!$A$2:$B$80,2, FALSE) -> Planting of crops in an area on ploughed land. | P37: =VLOOKUP(E37,Pressures!$A$2:$B$145,2,FALSE) -> Placement of seeds, seedlings or saplings into the ground so they can grow, leading to an increase in vegetation amount or a change in plant species composition. | V37: 111111 | X37: 123123 | AU37: 1 | AV37: 2 | AW37: 0 | AX37: 0 | AZ37: 1 | BA37: 2 | BB37: 3 | BE37: 112216 | CB37: 1615 | CC37: 1613 | CD37: 1612 | CE37: 1610 | CF37: 1513 | CG37: 1512 | CH37: 1510 | CI37: 1312 | CJ37: 1310 | EM37: 1 | ET37: =SUM(DO37:ES37) -> 1
A38: 15 | B38: Cropland gain | C38: agricultural expansion | D38: 3 | E38: Agricultural expansion | F38: Cropland gain (agricultural expansion) | G38: 37 | H38: =(A38*1000)+D38 -> 15003 | I38: White | J38: 255 | K38: 240 | L38: 0 | M38: 255 | N38: =G38&": ("&J38&", "&K38&", "&L38&", "&M38&", "&F38&": "&H38&")," -> 37: (255, 240, 0, 255, Cropland gain (agricultural expansion): 15003), | O38: =VLOOKUP(Australia!B38,Impacts!$A$2:$B$80,2, FALSE) -> Increase of total cropping area or total area sown. | P38: =VLOOKUP(E38,Pressures!$A$2:$B$145,2,FALSE) -> Increase in area of arable lands and pasture used for food production. | AE38: 112111 | AF38: 112123 | AG38: 124111 | AH38: 124123 | AU38: 1 | AV38: 2 | AW38: 0 | AX38: 0 | AZ38: 1 | BA38: 2 | BB38: 3 | BI38: 216216 | BZ38: 12 | CA38: 21 | EM38: 1 | ET38: =SUM(DO38:ES38) -> 1
A39: 15 | B39: Cropland gain | C39: farmland creation | D39: 42 | E39: Farmland creation | F39: Cropland gain (farmland creation) | G39: 38 | H39: =(A39*1000)+D39 -> 15042 | I39: Alice Blue | J39: 255 | K39: 182 | L39: 30 | M39: 255 | N39: =G39&": ("&J39&", "&K39&", "&L39&", "&M39&", "&F39&": "&H39&")," -> 38: (255, 182, 30, 255, Cropland gain (farmland creation): 15042), | O39: =VLOOKUP(Australia!B39,Impacts!$A$2:$B$80,2, FALSE) -> Increase of total cropping area or total area sown. | P39: =VLOOKUP(E39,Pressures!$A$2:$B$145,2,FALSE) -> Conversion of land to commercial, subsistence, intensive or extensive farming. | AE39: 112111 | AF39: 112123 | AG39: 124111 | AH39: 124123 | AU39: 1 | AV39: 2 | AW39: 0 | AX39: 0 | AZ39: 1 | BA39: 2 | BB39: 3 | BD39: 111111 | BE39: 112112 | BF39: 123123 | BG39: 124124 | BH39: 215215 | BI39: 216216 | BJ39: 227227 | BK39: 228228 | BL39: 220220 | BZ39: 12 | CA39: 21 | EM39: 1 | ET39: =SUM(DO39:ES39) -> 1
A40: 16 | B40: Cropland loss | C40: agricultural loss | D40: 4 | E40: Agricultural loss | F40: Cropland loss (agricultural loss) | G40: 39 | H40: =(A40*1000)+D40 -> 16004 | I40: Antique White | J40: 123 | K40: 63 | L40: 0 | M40: 255 | N40: =G40&": ("&J40&", "&K40&", "&L40&", "&M40&", "&F40&": "&H40&")," -> 39: (123, 63, 0, 255, Cropland loss (agricultural loss): 16004), | O40: =VLOOKUP(Australia!B40,Impacts!$A$2:$B$80,2, FALSE) -> Decrease of total cropping area or total area sown. | P40: =VLOOKUP(E40,Pressures!$A$2:$B$145,2,FALSE) -> Decrease in area of arable lands and pasture used for food production. | AE40: 111112 | AF40: 111124 | AG40: 123112 | AH40: 123124 | AW40: -1 | AX40: 0 | AZ40: 1 | BA40: 2 | BB40: 3 | BD40: 111111 | BE40: 112112 | BF40: 123123 | BG40: 124124 | BH40: 215215 | BI40: 216216 | BJ40: 227227 | BK40: 228228 | BL40: 220220 | EM40: 1 | ET40: =SUM(DO40:ES40) -> 1
A41: 16 | B41: Cropland loss | C41: animal stock change | D41: 7 | E41: Animal stock change | F41: Cropland loss (animal stock change) | G41: 40 | H41: =(A41*1000)+D41 -> 16007 | I41: Aqua | J41: 88 | K41: 41 | L41: 0 | M41: 255 | N41: =G41&": ("&J41&", "&K41&", "&L41&", "&M41&", "&F41&": "&H41&")," -> 40: (88, 41, 0, 255, Cropland loss (animal stock change): 16007), | O41: =VLOOKUP(Australia!B41,Impacts!$A$2:$B$80,2, FALSE) -> Decrease of total cropping area or total area sown. | P41: =VLOOKUP(E41,Pressures!$A$2:$B$145,2,FALSE) -> A change in the type of animal(s) obtaining food from an area. | AE41: 111112 | AF41: 111124 | AG41: 123112 | AH41: 123124 | AW41: 0 | AX41: 0 | AZ41: 1 | BA41: 2 | BB41: 3 | BD41: 111215 | BE41: 112215 | BF41: 123215 | BG41: 124215 | BH41: 215215 | BI41: 216216 | BL41: 220215 | EJ41: 1 | ET41: =SUM(DO41:ES41) -> 1
A42: 16 | B42: Cropland loss | C42: fallowing | D42: 40 | E42: Fallowing | F42: Cropland loss (fallowing) | G42: 41 | H42: =(A42*1000)+D42 -> 16040 | I42: Aquamarine | J42: 204 | K42: 119 | L42: 34 | M42: 255 | N42: =G42&": ("&J42&", "&K42&", "&L42&", "&M42&", "&F42&": "&H42&")," -> 41: (204, 119, 34, 255, Cropland loss (fallowing): 16040), | O42: =VLOOKUP(Australia!B42,Impacts!$A$2:$B$80,2, FALSE) -> Decrease of total cropping area or total area sown. | P42: =VLOOKUP(E42,Pressures!$A$2:$B$145,2,FALSE) -> A farming technique whereby a field is left unoccupied by crops during an entire growing period or part of it .. | AE42: 111112 | AF42: 111124 | AG42: 123112 | AH42: 123124 | AW42: 0 | AX42: 0 | AZ42: 1 | BA42: 2 | BB42: 3 | BD42: 111111 | BE42: 112112 | BF42: 123123 | BG42: 124124 | BH42: 215215 | BI42: 216216 | EM42: 1 | ET42: =SUM(DO42:ES42) -> 1
A43: 16 | B43: Cropland loss | C43: farmland abandonment | D43: 41 | E43: Farmland abandonment | F43: Cropland loss (farmland abandonment) | G43: 42 | H43: =(A43*1000)+D43 -> 16041 | I43: Azure | J43: 138 | K43: 121 | L43: 93 | M43: 255 | N43: =G43&": ("&J43&", "&K43&", "&L43&", "&M43&", "&F43&": "&H43&")," -> 42: (138, 121, 93, 255, Cropland loss (farmland abandonment): 16041), | O43: =VLOOKUP(Australia!B43,Impacts!$A$2:$B$80,2, FALSE) -> Decrease of total cropping area or total area sown. | P43: =VLOOKUP(E43,Pressures!$A$2:$B$145,2,FALSE) -> The cessation of agricultural activities on a given surface of land. | AE43: 111112 | AF43: 111124 | AG43: 123112 | AH43: 123124 | AW43: 0 | AX43: 0 | AZ43: 1 | BA43: 2 | BB43: 3 | BD43: 112215 | BE43: 112215 | BF43: 123215 | BG43: 124215 | BH43: 215215 | BI43: 216215 | BL43: 220215 | EM43: 1 | ET43: =SUM(DO43:ES43) -> 1
A44: 16 | B44: Cropland loss | C44: idle or fallow in rotation | D44: 58 | E44: Idle or fallow in rotation | F44: Cropland loss (idle or fallow in rotation) | G44: 43 | H44: =(A44*1000)+D44 -> 16058 | I44: Beige | J44: 245 | K44: 222 | L44: 179 | M44: 255 | N44: =G44&": ("&J44&", "&K44&", "&L44&", "&M44&", "&F44&": "&H44&")," -> 43: (245, 222, 179, 255, Cropland loss (idle or fallow in rotation): 16058), | O44: =VLOOKUP(Australia!B44,Impacts!$A$2:$B$80,2, FALSE) -> Decrease of total cropping area or total area sown. | P44: =VLOOKUP(E44,Pressures!$A$2:$B$145,2,FALSE) -> A crop sequence that includes idle, diverted, or fallowed land in 1 or more of the previous years. | V44: 111111 | X44: 123123 | AU44: 22 | AV44: 0 | AW44: 0 | AY44: 1 | AZ44: 2 | BA44: 3 | BH44: 216216 | BY44: 21 | EM44: 1 | ET44: =SUM(DO44:ES44) -> 1
A45: 17 | B45: Deglaciation | C45: prolonged temperature increase | D45: 97 | E45: Prolonged temperature increase | F45: Deglaciation (prolonged temperature increase) | G45: 44 | H45: =(A45*1000)+D45 -> 17097 | I45: Bisque | J45: 205 | K45: 149 | L45: 117 | M45: 255 | N45: =G45&": ("&J45&", "&K45&", "&L45&", "&M45&", "&F45&": "&H45&")," -> 44: (205, 149, 117, 255, Deglaciation (prolonged temperature increase): 17097), | O45: =VLOOKUP(Australia!B45,Impacts!$A$2:$B$80,2, FALSE) -> The uncovering of glaciated land because of melting or sublimation of the glacier. | P45: =VLOOKUP(E45,Pressures!$A$2:$B$145,2,FALSE) -> Seasonal to multi-annual increases in temperature compared with past averages. | AE45: 228112 | AF45: 228112 | AG45: 220112 | AH45: 220124 | AW45: 0 | AX45: 0 | AZ45: 1 | BA45: 2 | BB45: 3 | BD45: 111216 | BE45: 112216 | BF45: 112216 | BG45: 124216 | BI45: 216216 | DY45: 1 | DZ45: 1 | ET45: =SUM(DO45:ES45) -> 2
A46: 18 | B46: Desalinisation | C46: gypsum application | D46: 54 | E46: Gypsum application | F46: Desalinisation (gypsum application) | G46: 45 | H46: =(A46*1000)+D46 -> 18054 | I46: Blanched Almond | J46: 242 | K46: 240 | L46: 230 | M46: 255 | N46: =G46&": ("&J46&", "&K46&", "&L46&", "&M46&", "&F46&": "&H46&")," -> 45: (242, 240, 230, 255, Desalinisation (gypsum application): 18054), | O46: =VLOOKUP(Australia!B46,Impacts!$A$2:$B$80,2, FALSE) -> The process of soils becoming less salty. | P46: =VLOOKUP(E46,Pressures!$A$2:$B$145,2,FALSE) -> Spreading of a naturally occurring mineral that contains calcium and sulphur, thereby increasing porosity of the soil. | V46: 111111 | AW46: 0 | AX46: 0 | AZ46: 1 | BA46: 2 | BB46: 3 | BI46: 216216 | EM46: 1 | EN46: 1 | EP46: 1 | ET46: =SUM(DO46:ES46) -> 3
A47: 19 | B47: Desertification | C47: prolonged temperature increase | D47: 97 | E47: Prolonged temperature increase | F47: Desertification (prolonged temperature increase) | G47: 46 | H47: =(A47*1000)+D47 -> 19097 | I47: Blue Violet | J47: 255 | K47: 174 | L47: 66 | M47: 255 | N47: =G47&": ("&J47&", "&K47&", "&L47&", "&M47&", "&F47&": "&H47&")," -> 46: (255, 174, 66, 255, Desertification (prolonged temperature increase): 19097), | O47: =VLOOKUP(Australia!B47,Impacts!$A$2:$B$80,2, FALSE) -> Reduction in the productivity of the land that is not reversible. | P47: =VLOOKUP(E47,Pressures!$A$2:$B$145,2,FALSE) -> Seasonal to multi-annual increases in temperature compared with past averages. | W47: 112112 | AE47: 112216 | AW47: 0 | AX47: 0 | AZ47: 1 | BA47: 2 | BB47: 3 | BD47: 111216 | BE47: 112216 | BI47: 216216 | DY47: 1 | DZ47: 1 | ET47: =SUM(DO47:ES47) -> 2
A48: 20 | B48: Elevation change | C48: deposition | D48: 28 | E48: Deposition | F48: Elevation change (deposition) | G48: 47 | H48: =(A48*1000)+D48 -> 20028 | I48: Brown | J48: 159 | K48: 129 | L48: 112 | M48: 255 | N48: =G48&": ("&J48&", "&K48&", "&L48&", "&M48&", "&F48&": "&H48&")," -> 47: (159, 129, 112, 255, Elevation change (deposition): 20028), | O48: =VLOOKUP(Australia!B48,Impacts!$A$2:$B$80,2, FALSE) -> Change in the altitude above sea or ground level. | P48: =VLOOKUP(E48,Pressures!$A$2:$B$145,2,FALSE) -> Deposition is the laying down of sediment carried by wind, water, or ice. | AA48: 216216 | AW48: 0 | AX48: 0 | AZ48: 1 | BA48: 2 | BB48: 3 | BD48: 111216 | BE48: 112216 | BI48: 216216 | EB48: 1 | ET48: =SUM(DO48:ES48) -> 1
A49: 20 | B49: Elevation change | C49: earthquake | D49: 32 | E49: Earthquake | F49: Elevation change (earthquake) | G49: 48 | H49: =(A49*1000)+D49 -> 20032 | I49: Burlywood | J49: 222 | K49: 184 | L49: 135 | M49: 255 | N49: =G49&": ("&J49&", "&K49&", "&L49&", "&M49&", "&F49&": "&H49&")," -> 48: (222, 184, 135, 255, Elevation change (earthquake): 20032), | O49: =VLOOKUP(Australia!B49,Impacts!$A$2:$B$80,2, FALSE) -> Change in the altitude above sea or ground level. | P49: =VLOOKUP(E49,Pressures!$A$2:$B$145,2,FALSE) -> The vibrations of the Earth caused by the passage of seismic waves radiating from some source of elastic energy. | V49: 111111 | W49: 112112 | X49: 123123 | Y49: 124124 | Z49: 215215 | AA49: 216216 | AW49: 0 | AX49: 0 | AZ49: 1 | BA49: 2 | BB49: 3 | BG49: 124216 | BI49: 216216 | EF49: 1 | ET49: =SUM(DO49:ES49) -> 1
A50: 20 | B50: Elevation change | C50: landslide | D50: 73 | E50: Landslide | F50: Elevation change (landslide) | G50: 49 | H50: =(A50*1000)+D50 -> 20073 | I50: Cadet Blue | J50: 255 | K50: 228 | L50: 196 | M50: 255 | N50: =G50&": ("&J50&", "&K50&", "&L50&", "&M50&", "&F50&": "&H50&")," -> 49: (255, 228, 196, 255, Elevation change (landslide): 20073), | O50: =VLOOKUP(Australia!B50,Impacts!$A$2:$B$80,2, FALSE) -> Change in the altitude above sea or ground level. | P50: =VLOOKUP(E50,Pressures!$A$2:$B$145,2,FALSE) -> Movement of material downslope in a mass. | V50: 111111 | W50: 112112 | X50: 123123 | Y50: 124124 | Z50: 215215 | AA50: 216216 | AW50: 0 | AX50: 0 | AZ50: 1 | BA50: 2 | BB50: 3 | BI50: 216216 | DS50: 1 | EB50: 1 | EF50: 1 | ET50: =SUM(DO50:ES50) -> 3
A51: 20 | B51: Elevation change | C51: mining | D51: 80 | E51: Mining | F51: Elevation change (mining) | G51: 50 | H51: =(A51*1000)+D51 -> 20080 | I51: Chartreuse | J51: 210 | K51: 105 | L51: 30 | M51: 255 | N51: =G51&": ("&J51&", "&K51&", "&L51&", "&M51&", "&F51&": "&H51&")," -> 50: (210, 105, 30, 255, Elevation change (mining): 20080), | O51: =VLOOKUP(Australia!B51,Impacts!$A$2:$B$80,2, FALSE) -> Change in the altitude above sea or ground level. | P51: =VLOOKUP(E51,Pressures!$A$2:$B$145,2,FALSE) -> Extraction of minerals, precious stones or coal, either through open cuts or deep shafts. | V51: 111111 | W51: 112112 | X51: 123123 | Y51: 124124 | Z51: 215215 | AA51: 216216 | AW51: 0 | AX51: 0 | AZ51: 1 | BA51: 2 | BB51: 3 | BD51: 112216 | BE51: 11216 | BF51: 123216 | BG51: 124216 | BH51: 215216 | BI51: 216216 | EK51: 1 | ET51: =SUM(DO51:ES51) -> 1
A52: 20 | B52: Elevation change | C52: subsidence | D52: 122 | E52: Subsidence | F52: Elevation change (subsidence) | G52: 51 | H52: =(A52*1000)+D52 -> 20122 | I52: Chocolate | J52: 119 | K52: 63 | L52: 26 | M52: 255 | N52: =G52&": ("&J52&", "&K52&", "&L52&", "&M52&", "&F52&": "&H52&")," -> 51: (119, 63, 26, 255, Elevation change (subsidence): 20122), | O52: =VLOOKUP(Australia!B52,Impacts!$A$2:$B$80,2, FALSE) -> Change in the altitude above sea or ground level. | P52: =VLOOKUP(E52,Pressures!$A$2:$B$145,2,FALSE) -> The lowering of the Earth's surface, caused by factors such as compaction, a decrease in ground water or earthquakes. | V52: 111111 | W52: 112112 | X52: 123123 | Y52: 124124 | Z52: 215215 | AA52: 216216 | AW52: 0 | AX52: 0 | AZ52: 1 | BA52: 2 | BB52: 3 | BG52: 124216 | BI52: 216216 | EF52: 1 | EK52: 1 | ET52: =SUM(DO52:ES52) -> 2
A53: 20 | B53: Elevation change | C53: waste dumping | D53: 138 | E53: Waste dumping | F53: Elevation change (waste dumping) | G53: 52 | H53: =(A53*1000)+D53 -> 20138 | I53: Coral | J53: 170 | K53: 64 | L53: 105 | M53: 255 | N53: =G53&": ("&J53&", "&K53&", "&L53&", "&M53&", "&F53&": "&H53&")," -> 52: (170, 64, 105, 255, Elevation change (waste dumping): 20138), | O53: =VLOOKUP(Australia!B53,Impacts!$A$2:$B$80,2, FALSE) -> Change in the altitude above sea or ground level. | P53: =VLOOKUP(E53,Pressures!$A$2:$B$145,2,FALSE) -> The disposal of solid wastes without environmental controls. | Z53: 215215 | AE53: 111215 | AF53: 112215 | AG53: 123215 | AH53: 124215 | AW53: 0 | AX53: 0 | AZ53: 1 | BA53: 2 | BB53: 3 | BD53: 112220 | BE53: 112220 | BF53: 123220 | BG53: 124220 | BH53: 215220 | BI53: 216220 | BL53: 220220 | DA53: 11 | EL53: 1 | ET53: =SUM(DO53:ES53) -> 1
A54: 21 | B54: Erosion | C54: construction | D54: 16 | E54: Construction | F54: Erosion (construction) | G54: 53 | H54: =(A54*1000)+D54 -> 21016 | I54: Cornsilk | J54: 150 | K54: 0 | L54: 24 | M54: 255 | N54: =G54&": ("&J54&", "&K54&", "&L54&", "&M54&", "&F54&": "&H54&")," -> 53: (150, 0, 24, 255, Erosion (construction): 21016), | O54: =VLOOKUP(Australia!B54,Impacts!$A$2:$B$80,2, FALSE) -> Geological process in which earthen materials are worn away and transported by natural forces. | P54: =VLOOKUP(E54,Pressures!$A$2:$B$145,2,FALSE) -> Creation of infrastructure such as railways, roads, mines, buildings, agricultural farms, aquaculture farms or dams. | AB54: 227227 | AC54: 228228 | AD54: 220220 | AW54: 0 | AX54: 0 | AZ54: 1 | BA54: 2 | BB54: 3 | BD54: 111215 | BE54: 112215 | BF54: 123215 | BG54: 124215 | BH54: 215215 | BI54: 216215 | EL54: 1 | ET54: =SUM(DO54:ES54) -> 1
A55: 21 | B55: Erosion | C55: excess precipitation | D55: 38 | E55: Excess precipitation | F55: Erosion (excess precipitation) | G55: 54 | H55: =(A55*1000)+D55 -> 21038 | I55: Crimson | J55: 145 | K55: 95 | L55: 109 | M55: 255 | N55: =G55&": ("&J55&", "&K55&", "&L55&", "&M55&", "&F55&": "&H55&")," -> 54: (145, 95, 109, 255, Erosion (excess precipitation): 21038), | O55: =VLOOKUP(Australia!B55,Impacts!$A$2:$B$80,2, FALSE) -> Geological process in which earthen materials are worn away and transported by natural forces. | P55: =VLOOKUP(E55,Pressures!$A$2:$B$145,2,FALSE) -> Above-normal increase in the amount of rain or snowfall. | AE55: 111216 | AF55: 112216 | AG55: 123216 | AH55: 124216 | AI55: 215216 | AW55: -1 | AX55: 0 | AZ55: 1 | BA55: 2 | BB55: 3 | BE55: 112220 | BG55: 124220 | BI55: 216220 | EB55: 1 | ET55: =SUM(DO55:ES55) -> 1
A56: 21 | B56: Erosion | C56: frost | D56: 46 | E56: Frost | F56: Erosion (frost) | G56: 55 | H56: =(A56*1000)+D56 -> 21046 | I56: Dark Blue | J56: 162 | K56: 162 | L56: 208 | M56: 255 | N56: =G56&": ("&J56&", "&K56&", "&L56&", "&M56&", "&F56&": "&H56&")," -> 55: (162, 162, 208, 255, Erosion (frost): 21046), | O56: =VLOOKUP(Australia!B56,Impacts!$A$2:$B$80,2, FALSE) -> Geological process in which earthen materials are worn away and transported by natural forces. | P56: =VLOOKUP(E56,Pressures!$A$2:$B$145,2,FALSE) -> Deposit of soft white ice crystals or frozen dew drops on objects near the ground; formed when surface temperature falls below freezing point. | AA56: 216216 | AW56: 0 | AX56: 0 | AZ56: 1 | BA56: 2 | BB56: 3 | BD56: 111111 | BE56: 112112 | BF56: 123123 | BG56: 124124 | BV56: 22 | BX56: □+ | BY56: □+ | DZ56: 1 | ET56: =SUM(DO56:ES56) -> 1
A57: 21 | B57: Erosion | C57: increased traffic | D57: 65 | E57: Increased traffic | F57: Erosion (increased traffic) | G57: 56 | H57: =(A57*1000)+D57 -> 21065 | I57: Dark Cyan | J57: 212 | K57: 112 | L57: 162 | M57: 255 | N57: =G57&": ("&J57&", "&K57&", "&L57&", "&M57&", "&F57&": "&H57&")," -> 56: (212, 112, 162, 255, Erosion (increased traffic): 21065), | O57: =VLOOKUP(Australia!B57,Impacts!$A$2:$B$80,2, FALSE) -> Geological process in which earthen materials are worn away and transported by natural forces. | P57: =VLOOKUP(E57,Pressures!$A$2:$B$145,2,FALSE) -> A greater number of vehicles moving along roads, or the amount of aircraft, trains, or ships moving along a route. | AE57: 111216 | AF57: 112216 | AG57: 123216 | AH57: 124216 | AW57: 0 | AX57: 0 | AZ57: 1 | BA57: 2 | BB57: 3 | BL57: 220220 | EQ57: 1 | ET57: =SUM(DO57:ES57) -> 1
A58: 21 | B58: Erosion | C58: increased wind | D58: 66 | E58: Increased wind | F58: Erosion (increased wind) | G58: 57 | H58: =(A58*1000)+D58 -> 21066 | I58: Dark Goldenrod | J58: 153 | K58: 102 | L58: 204 | M58: 255 | N58: =G58&": ("&J58&", "&K58&", "&L58&", "&M58&", "&F58&": "&H58&")," -> 57: (153, 102, 204, 255, Erosion (increased wind): 21066), | O58: =VLOOKUP(Australia!B58,Impacts!$A$2:$B$80,2, FALSE) -> Geological process in which earthen materials are worn away and transported by natural forces. | P58: =VLOOKUP(E58,Pressures!$A$2:$B$145,2,FALSE) -> A higher velocity of air movement into an area associated with, for example, cyclones, hurricans, typhoons, tornados, thunderstorms, storms or ice storms. | AA58: 216216 | AW58: 0 | AX58: 0 | AZ58: 1 | BA58: 2 | BB58: 3 | BD58: 111220 | BE58: 112220 | BF58: 123220 | BG58: 124220 | BH58: 215220 | BI58: 216220 | BL58: 220220 | EC58: 1 | ET58: =SUM(DO58:ES58) -> 1
A59: 21 | B59: Erosion | C59: sea level fluctuation | D59: 110 | E59: Sea level fluctuation | F59: Erosion (sea level fluctuation) | G59: 58 | H59: =(A59*1000)+D59 -> 21110 | I59: Dark Gray | J59: 162 | K59: 173 | L59: 208 | M59: 255 | N59: =G59&": ("&J59&", "&K59&", "&L59&", "&M59&", "&F59&": "&H59&")," -> 58: (162, 173, 208, 255, Erosion (sea level fluctuation): 21110), | O59: =VLOOKUP(Australia!B59,Impacts!$A$2:$B$80,2, FALSE) -> Geological process in which earthen materials are worn away and transported by natural forces. | P59: =VLOOKUP(E59,Pressures!$A$2:$B$145,2,FALSE) -> Irregular rise and fall of sea level. | AA59: 216216 | AE59: 111216 | AF59: 112216 | AG59: 123216 | AH59: 124216 | AI59: 215216 | AW59: 0 | AX59: 0 | AZ59: 1 | BA59: 2 | BB59: 3 | DS59: 1 | EE59: 1 | ET59: =SUM(DO59:ES59) -> 2
A60: 21 | B60: Erosion | C60: topsoil removal | D60: 127 | E60: Topsoil removal | F60: Erosion (topsoil removal) | G60: 59 | H60: =(A60*1000)+D60 -> 21127 | I60: Dark Green | J60: 115 | K60: 54 | L60: 53 | M60: 255 | N60: =G60&": ("&J60&", "&K60&", "&L60&", "&M60&", "&F60&": "&H60&")," -> 59: (115, 54, 53, 255, Erosion (topsoil removal): 21127), | O60: =VLOOKUP(Australia!B60,Impacts!$A$2:$B$80,2, FALSE) -> Geological process in which earthen materials are worn away and transported by natural forces. | P60: =VLOOKUP(E60,Pressures!$A$2:$B$145,2,FALSE) -> Taking away the surface layer of soil that contains partly decomposed organic debris. | AE60: 111216 | AF60: 123216 | AW60: 0 | AX60: 0 | AZ60: 1 | BA60: 2 | BB60: 3 | BD60: 111216 | BE60: 112216 | BF60: 123216 | BG60: 124216 | BH60: 215216 | BI60: 216216 | BL60: 220216 | EK60: 1 | EL60: 1 | EM60: 1 | ET60: =SUM(DO60:ES60) -> 3
A61: 21 | B61: Erosion | C61: water movement change | D61: 140 | E61: Water movement change | F61: Erosion (water movement change) | G61: 60 | H61: =(A61*1000)+D61 -> 21140 | I61: Dark Magenta | J61: 26 | K61: 72 | L61: 118 | M61: 255 | N61: =G61&": ("&J61&", "&K61&", "&L61&", "&M61&", "&F61&": "&H61&")," -> 60: (26, 72, 118, 255, Erosion (water movement change): 21140), | O61: =VLOOKUP(Australia!B61,Impacts!$A$2:$B$80,2, FALSE) -> Geological process in which earthen materials are worn away and transported by natural forces. | P61: =VLOOKUP(E61,Pressures!$A$2:$B$145,2,FALSE) -> A change in the direction of flow of a body of water that might be accompanied by a change in velocity, turbulence and/or discharge. | AB61: 227227 | AC61: 228228 | AD61: 220220 | AE61: 111216 | AF61: 112216 | AG61: 123216 | AH61: 124216 | AI61: 215216 | AJ61: 112228 | AK61: 123228 | AL61: 124228 | AM61: 215228 | AN61: 216228 | AO61: 111220 | AP61: 112220 | AQ61: 123220 | AR61: 124220 | AS61: 215220 | AT61: 216220 | AW61: 0 | AX61: 0 | AZ61: 1 | BA61: 2 | BB61: 3 | DA61: 11 | DT61: 1 | ET61: =SUM(DO61:ES61) -> 1
A62: 21 | B62: Erosion | C62: wave action | D62: 139 | E62: Wave action | F62: Erosion (wave action) | G62: 61 | H62: =(A62*1000)+D62 -> 21139 | I62: Dark Orange | J62: 106 | K62: 90 | L62: 205 | M62: 255 | N62: =G62&": ("&J62&", "&K62&", "&L62&", "&M62&", "&F62&": "&H62&")," -> 61: (106, 90, 205, 255, Erosion (wave action): 21139), | O62: =VLOOKUP(Australia!B62,Impacts!$A$2:$B$80,2, FALSE) -> Geological process in which earthen materials are worn away and transported by natural forces. | P62: =VLOOKUP(E62,Pressures!$A$2:$B$145,2,FALSE) -> Disturbance on the surface of a liquid body, as the sea or a lake, in the form of a moving ridge or swell that impacts on the structure of land elements. | AB62: 227227 | AC62: 228228 | AD62: 220220 | AE62: 111216 | AF62: 112216 | AG62: 123216 | AH62: 124216 | AI62: 215216 | AJ62: 112228 | AK62: 123228 | AL62: 124228 | AM62: 215228 | AN62: 216228 | AO62: 111220 | AP62: 112220 | AQ62: 123220 | AR62: 124220 | AS62: 215220 | AT62: 216220 | AW62: 0 | AX62: 0 | AZ62: 1 | BA62: 2 | BB62: 3 | BH62: 215215 | DA62: 11 | EE62: 1 | ET62: =SUM(DO62:ES62) -> 1
A63: 22 | B63: Flooding | C63: excess rain | D63: 39 | E63: Excess rain | F63: Flooding (excess rain) | G63: 62 | H63: =(A63*1000)+D63 -> 22039 | I63: Dark Red | J63: 111 | K63: 0 | L63: 255 | M63: 255 | N63: =G63&": ("&J63&", "&K63&", "&L63&", "&M63&", "&F63&": "&H63&")," -> 62: (111, 0, 255, 255, Flooding (excess rain): 22039), | O63: =VLOOKUP(Australia!B63,Impacts!$A$2:$B$80,2, FALSE) -> Inundation of water over an area. | P63: =VLOOKUP(E63,Pressures!$A$2:$B$145,2,FALSE) -> Heavy rainfall associated with the passage of a storm or tropical cyclone than can produce extensive flooding. | AE63: 112228 | AF63: 123228 | AG63: 124228 | AH63: 215228 | AI63: 216228 | AJ63: 111220 | AK63: 112220 | AL63: 123220 | AM63: 124220 | AN63: 215220 | AO63: 216220 | AW63: 1 | AX63: 0 | AZ63: 1 | BA63: 2 | BB63: 3 | BD63: 111215 | BE63: 112215 | BF63: 123215 | BG63: 124215 | BH63: 215215 | BI63: 216215 | BL63: 220215 | EB63: 1 | ET63: =SUM(DO63:ES63) -> 1
A64: 22 | B64: Flooding | C64: snowmelt | D64: 123 | E64: Snowmelt | F64: Flooding (excess snow) | G64: 63 | H64: =(A64*1000)+D64 -> 22123 | I64: Dark Salmon | J64: 135 | K64: 206 | L64: 235 | M64: 255 | N64: =G64&": ("&J64&", "&K64&", "&L64&", "&M64&", "&F64&": "&H64&")," -> 63: (135, 206, 235, 255, Flooding (excess snow): 22123), | O64: =VLOOKUP(Australia!B64,Impacts!$A$2:$B$80,2, FALSE) -> Inundation of water over an area. | P64: =VLOOKUP(E64,Pressures!$A$2:$B$145,2,FALSE) -> Water produced by the melting of snow. | AE64: 112228 | AF64: 123228 | AG64: 124228 | AH64: 215228 | AI64: 216228 | AJ64: 111220 | AK64: 112220 | AL64: 123220 | AM64: 124220 | AN64: 215220 | AO64: 216220 | DU64: 1 | DY64: 1 | ET64: =SUM(DO64:ES64) -> 2
A65: 23 | B65: Geomorphological change | C65: mining | D65: 80 | E65: Mining | F65: Geomorphological change (mining) | G65: 64 | H65: =(A65*1000)+D65 -> 23080 | I65: Dark Sea Green | J65: 141 | K65: 43 | L65: 11 | M65: 255 | N65: =G65&": ("&J65&", "&K65&", "&L65&", "&M65&", "&F65&": "&H65&")," -> 64: (141, 43, 11, 255, Geomorphological change (mining): 23080), | O65: =VLOOKUP(Australia!B65,Impacts!$A$2:$B$80,2, FALSE) -> A geomorphic adjustment that changes the geometry of landforms. | P65: =VLOOKUP(E65,Pressures!$A$2:$B$145,2,FALSE) -> Extraction of minerals, precious stones or coal, either through open cuts or deep shafts. | AE65: 111215 | AF65: 112215 | AG65: 123215 | AH65: 124215 | AI65: 215215 | AW65: 1 | AX65: 0 | AZ65: 1 | BA65: 2 | BB65: 3 | BI65: 216216 | EK65: 1 | ET65: =SUM(DO65:ES65) -> 1
A66: 24 | B66: Glaciation | C66: prolonged temperature decrease | D66: 96 | E66: Prolonged temperature decrease | F66: Glaciation (prolonged temperature decrease) | G66: 65 | H66: =(A66*1000)+D66 -> 24096 | I66: Dark Slate Blue | J66: 176 | K66: 224 | L66: 230 | M66: 255 | N66: =G66&": ("&J66&", "&K66&", "&L66&", "&M66&", "&F66&": "&H66&")," -> 65: (176, 224, 230, 255, Glaciation (prolonged temperature decrease): 24096), | O66: =VLOOKUP(Australia!B66,Impacts!$A$2:$B$80,2, FALSE) -> Expansion of ice or glacier cover. | P66: =VLOOKUP(E66,Pressures!$A$2:$B$145,2,FALSE) -> Seasonal to multi-annual decreases in temperature compared with past averages. | AE66: 112228 | AF66: 123228 | AG66: 124228 | AH66: 215228 | AI66: 216220 | AJ66: 111220 | AK66: 112220 | AL66: 123220 | AM66: 124220 | AN66: 215220 | AO66: 216220 | AW66: 1 | AX66: 0 | AZ66: 1 | BA66: 2 | BB66: 3 | BH66: 215215 | CZ66: 3 | DY66: 1 | DZ66: 1 | ET66: =SUM(DO66:ES66) -> 2
A67: 25 | B67: Greening | C67: increased precipitation | D67: 63 | E67: Increased precipitation | F67: Greening (increased precipitation) | G67: 66 | H67: =(A67*1000)+D67 -> 25063 | I67: Dark Slate Gray | J67: 154 | K67: 205 | L67: 50 | M67: 255 | N67: =G67&": ("&J67&", "&K67&", "&L67&", "&M67&", "&F67&": "&H67&")," -> 66: (154, 205, 50, 255, Greening (increased precipitation): 25063), | O67: =VLOOKUP(Australia!B67,Impacts!$A$2:$B$80,2, FALSE) -> An increase in the amount of photosynthetically active pigments in vegetation. | P67: =VLOOKUP(E67,Pressures!$A$2:$B$145,2,FALSE) -> Increased condensation of water vapour in the atmosphere forming rain, snow, sleet or dew. | V67: 111111 | W67: 112112 | X67: 123123 | Y67: 124124 | AU67: 1 | AV67: 2 | AW67: 0 | AY67: 1 | AZ67: 2 | BA67: 3 | BG67: 215215 | BY67: 2 | BZ67: 12 | CB67: 1615 | CC67: 1613 | CD67: 1612 | CE67: 1610 | CF67: 1513 | CG67: 1512 | CH67: 1510 | CI67: 1312 | CJ67: 1310 | EB67: 1 | ET67: =SUM(DO67:ES67) -> 1
A68: 26 | B68: Increased sediment load | C68: sediment transport | D68: 111 | E68: Sediment transport | F68: Increased sediment load (sediment transport) | G68: 67 | H68: =(A68*1000)+D68 -> 26111 | I68: Dark Turquoise | J68: 184 | K68: 134 | L68: 11 | M68: 255 | N68: =G68&": ("&J68&", "&K68&", "&L68&", "&M68&", "&F68&": "&H68&")," -> 67: (184, 134, 11, 255, Increased sediment load (sediment transport): 26111), | O68: =VLOOKUP(Australia!B68,Impacts!$A$2:$B$80,2, FALSE) -> Increase in the amount of a substance discharged into a body of water. | P68: =VLOOKUP(E68,Pressures!$A$2:$B$145,2,FALSE) -> The movement of solid particles (sediment) caused by movement of the water volume within which they are contained and the force of gravity. | AB68: 227227 | AC68: 228228 | AD68: 220220 | AW68: 0 | AY68: 1 | AZ68: 2 | BA68: 3 | BC68: 111220 | BD68: 112220 | BE68: 123220 | BF68: 124220 | BG68: 215220 | BH68: 216220 | CZ68: 11 | DA68: 11 | DV68: 1 | ET68: =SUM(DO68:ES68) -> 1
A69: 27 | B69: Inundation | C69: flooding | D69: 44 | E69: Flooding | F69: Inundation (flooding) | G69: 68 | H69: =(A69*1000)+D69 -> 27044 | I69: Dark Violet | J69: 30 | K69: 144 | L69: 255 | M69: 255 | N69: =G69&": ("&J69&", "&K69&", "&L69&", "&M69&", "&F69&": "&H69&")," -> 68: (30, 144, 255, 255, Inundation (flooding): 27044), | O69: =VLOOKUP(Australia!B69,Impacts!$A$2:$B$80,2, FALSE) -> Progressive submergence of land or structures through flooding. | P69: =VLOOKUP(E69,Pressures!$A$2:$B$145,2,FALSE) -> The inundation of water over land that is generally dry. | AE69: 112228 | AF69: 123228 | AG69: 124228 | AH69: 215228 | AI69: 216228 | AJ69: 111220 | AK69: 112220 | AL69: 123220 | AM69: 124220 | AN69: 215220 | AO69: 216220 | AW69: 0 | AY69: 1 | AZ69: 2 | BA69: 3 | BK69: 220220 | DS69: 1 | ET69: =SUM(DO69:ES69) -> 1
A70: 27 | B70: Inundation | C70: sea level fluctuation | D70: 68 | E70: Sea level fluctuation | F70: Inundation (sea level fluctuation) | G70: 69 | H70: =(A70*1000)+D70 -> 27068 | I70: Deep Pink | J70: 0 | K70: 206 | L70: 209 | M70: 255 | N70: =G70&": ("&J70&", "&K70&", "&L70&", "&M70&", "&F70&": "&H70&")," -> 69: (0, 206, 209, 255, Inundation (sea level fluctuation): 27068), | O70: =VLOOKUP(Australia!B70,Impacts!$A$2:$B$80,2, FALSE) -> Progressive submergence of land or structures through flooding. | P70: =VLOOKUP(E70,Pressures!$A$2:$B$145,2,FALSE) -> Irregular rise and fall of sea level. | AE70: 112228 | AF70: 123228 | AG70: 124228 | AH70: 215228 | AI70: 216228 | AJ70: 111220 | AK70: 112220 | AL70: 123220 | AM70: 124220 | AN70: 215220 | AO70: 216220 | AW70: 0 | AY70: 1 | AZ70: 2 | BA70: 3 | BL70: 220111 | BM70: 220112 | BN70: 220123 | BO70: 220124 | BP70: 220215 | BQ70: 220216 | EE70: 1 | ET70: =SUM(DO70:ES70) -> 1
A71: 28 | B71: Lava flow | C71: volcanic eruption | D71: 137 | E71: Volcanic eruption | F71: Lava flow (volcanic eruption) | G71: 70 | H71: =(A71*1000)+D71 -> 28137 | I71: Deep Sky Blue | J71: 207 | K71: 16 | L71: 32 | M71: 255 | N71: =G71&": ("&J71&", "&K71&", "&L71&", "&M71&", "&F71&": "&H71&")," -> 70: (207, 16, 32, 255, Lava flow (volcanic eruption): 28137), | O71: =VLOOKUP(Australia!B71,Impacts!$A$2:$B$80,2, FALSE) -> A mass of molten rock produced during the eruption of a volcano and moving down its sides. | P71: =VLOOKUP(E71,Pressures!$A$2:$B$145,2,FALSE) -> The discharge (aerially explosive) of fragmentary ejecta, lava and gases from a volcanic vent. | AA71: 216216 | AE71: 111216 | AF71: 112216 | AG71: 123216 | AH71: 124216 | AI71: 215216 | AW71: 0 | AY71: 1 | AZ71: 2 | BA71: 3 | BK71: 220220 | DO71: 1 | DQ71: 1 | ET71: =SUM(DO71:ES71) -> 2
A72: 29 | B72: Leaf scorch | C72: strong winds | D72: 120 | E72: Strong winds | F72: Leaf scorch (strong winds) | G72: 71 | H72: =(A72*1000)+D72 -> 29120 | I72: Dim Gray | J72: 196 | K72: 98 | L72: 16 | M72: 255 | N72: =G72&": ("&J72&", "&K72&", "&L72&", "&M72&", "&F72&": "&H72&")," -> 71: (196, 98, 16, 255, Leaf scorch (strong winds): 29120), | O72: =VLOOKUP(Australia!B72,Impacts!$A$2:$B$80,2, FALSE) -> A non-infectious, physiological condition caused by unfavorable environmental situations. | P72: =VLOOKUP(E72,Pressures!$A$2:$B$145,2,FALSE) -> A prolonged period of average wind speeds exceeding 40km/h during the day. | V72: 111111 | W72: 112112 | X72: 123123 | Y72: 124124 | AU72: 11 | AW72: 0 | AY72: 1 | AZ72: 2 | BA72: 3 | BD72: 112112 | BF72: 124124 | BU72: 22 | BY72: 22 | CB72: 1012 | CC72: 1013 | CD72: 1015 | CE72: 1016 | CF72: 1213 | CG72: 1215 | CH72: 1216 | CI72: 1315 | CJ72: 1316 | CK72: 1516 | EC72: 1 | ET72: =SUM(DO72:ES72) -> 1
A73: 30 | B73: Mine abandonment | C73: reduced investment | D73: 98 | E73: Reduced investment | F73: Mine abandonment (reduced investment) | G73: 72 | H73: =(A73*1000)+D73 -> 30098 | I73: Dodger Blue | J73: 179 | K73: 68 | L73: 108 | M73: 255 | N73: =G73&": ("&J73&", "&K73&", "&L73&", "&M73&", "&F73&": "&H73&")," -> 72: (179, 68, 108, 255, Mine abandonment (reduced investment): 30098), | O73: =VLOOKUP(Australia!B73,Impacts!$A$2:$B$80,2, FALSE) -> Land formally used for extractive industry but no longer in use and no new use observed. | P73: =VLOOKUP(E73,Pressures!$A$2:$B$145,2,FALSE) -> Sale of an asset or item or removing funding from a service. | AE73: 216112 | AF73: 216124 | AG73: 216215 | AW73: 1 | AX73: 0 | AZ73: 1 | BA73: 2 | BB73: 3 | BH73: 215215 | BN73: 215112 | BP73: 215112 | EK73: 1 | ET73: =SUM(DO73:ES73) -> 1
A74: 31 | B74: Mine expansion | C74: increased investment | D74: 61 | E74: Increased investment | F74: Mine expansion (increased investment) | G74: 73 | H74: =(A74*1000)+D74 -> 31061 | I74: Firebrick | J74: 196 | K74: 174 | L74: 173 | M74: 255 | N74: =G74&": ("&J74&", "&K74&", "&L74&", "&M74&", "&F74&": "&H74&")," -> 73: (196, 174, 173, 255, Mine expansion (increased investment): 31061), | O74: =VLOOKUP(Australia!B74,Impacts!$A$2:$B$80,2, FALSE) -> Design and construction of landforms as well as the establishment of sustainable ecosystems or alternative vegetation. | P74: =VLOOKUP(E74,Pressures!$A$2:$B$145,2,FALSE) -> Purchase of an asset, item or service. | AE74: 111215 | AF74: 112215 | AG74: 123215 | AH74: 124215 | AI74: 216215 | AW74: 1 | AX74: 0 | AZ74: 1 | BA74: 2 | BB74: 3 | BD74: 111215 | BE74: 112215 | BF74: 123215 | BG74: 124215 | BH74: 215215 | BI74: 216215 | BL74: 220215 | EK74: 1 | ET74: =SUM(DO74:ES74) -> 1
A75: 32 | B75: Natural surface gain | C75: deposition | D75: 28 | E75: Deposition | F75: Natural surface gain (deposition) | G75: 74 | H75: =(A75*1000)+D75 -> 32028 | I75: Floral White | J75: 255 | K75: 218 | L75: 191 | M75: 255 | N75: =G75&": ("&J75&", "&K75&", "&L75&", "&M75&", "&F75&": "&H75&")," -> 74: (255, 218, 191, 255, Natural surface gain (deposition): 32028), | O75: =VLOOKUP(Australia!B75,Impacts!$A$2:$B$80,2, FALSE) -> Increase in the area occupied by a natural surface. | P75: =VLOOKUP(E75,Pressures!$A$2:$B$145,2,FALSE) -> Deposition is the laying down of sediment carried by wind, water, or ice. | AA75: 216216 | AW75: 1 | AX75: 0 | AZ75: 1 | BA75: 2 | BB75: 3 | BM75: 220111 | BN75: 220112 | BO75: 220123 | BP75: 220214 | BQ75: 220215 | BR75: 220216 | DV75: 1 | ET75: =SUM(DO75:ES75) -> 1
A76: 32 | B76: Natural surface gain | C76: urban rehabilitation | D76: 133 | E76: Urban rehabilitation | F76: Natural surface gain (urban rehabilitation) | G76: 75 | H76: =(A76*1000)+D76 -> 32133 | I76: Forest Green | J76: 240 | K76: 230 | L76: 140 | M76: 255 | N76: =G76&": ("&J76&", "&K76&", "&L76&", "&M76&", "&F76&": "&H76&")," -> 75: (240, 230, 140, 255, Natural surface gain (urban rehabilitation): 32133), | O76: =VLOOKUP(Australia!B76,Impacts!$A$2:$B$80,2, FALSE) -> Increase in the area occupied by a natural surface. | P76: =VLOOKUP(E76,Pressures!$A$2:$B$145,2,FALSE) -> Area devoted to regenerating and conserving the built heritage or the urban environment, including the ecosystems. | Z76: 215215 | AW76: 1 | AX76: 0 | AZ76: 1 | BA76: 2 | BB76: 3 | BL76: 220220 | EL76: 1 | ET76: =SUM(DO76:ES76) -> 1
A77: 33 | B77: Natural surface loss | C77: mining | D77: 80 | E77: Mining | F77: Natural surface loss (mining) | G77: 76 | H77: =(A77*1000)+D77 -> 33080 | I77: Gainsboro | J77: 102 | K77: 51 | L77: 153 | M77: 255 | N77: =G77&": ("&J77&", "&K77&", "&L77&", "&M77&", "&F77&": "&H77&")," -> 76: (102, 51, 153, 255, Natural surface loss (mining): 33080), | O77: =VLOOKUP(Australia!B77,Impacts!$A$2:$B$80,2, FALSE) -> Decrease in area of natural surface. | P77: =VLOOKUP(E77,Pressures!$A$2:$B$145,2,FALSE) -> Extraction of minerals, precious stones or coal, either through open cuts or deep shafts. | Z77: 215215 | AE77: 111215 | AF77: 112215 | AG77: 123215 | AH77: 124215 | AI77: 216215 | AW77: 1 | AX77: 0 | AZ77: 1 | BA77: 2 | BB77: 3 | BD77: 111111 | BE77: 112112 | BF77: 123123 | BG77: 124124 | BI77: 216216 | BV77: 22 | BX77: △ | BY77: △ | EK77: 1 | ET77: =SUM(DO77:ES77) -> 1
A78: 34 | B78: Net snow gain - amount | C78: snowfall | D78: 121 | E78: Snowfall | F78: Net snow gain (amount) (snowfall) | G78: 77 | H78: =(A78*1000)+D78 -> 34121 | I78: Gold | J78: 255 | K78: 250 | L78: 250 | M78: 255 | N78: =G78&": ("&J78&", "&K78&", "&L78&", "&M78&", "&F78&": "&H78&")," -> 77: (255, 250, 250, 255, Net snow gain (amount) (snowfall): 34121), | O78: =VLOOKUP(Australia!B78,Impacts!$A$2:$B$80,2, FALSE) -> Increase in the quantity of snow | P78: =VLOOKUP(E78,Pressures!$A$2:$B$145,2,FALSE) -> Where water vapour turns into solid ice crystals and falls as snow. | AC78: 228228 | AD78: 220220 | CZ78: 2 | DZ78: 1 | EB78: 1 | ET78: =SUM(DO78:ES78) -> 2
A79: 35 | B79: Net snow loss - amount | C79: snowmelt | D79: 123 | E79: Snowmelt | F79: Net snow loss (amount) (snowmelt) | G79: 78 | H79: =(A79*1000)+D79 -> 35123 | I79: Goldenrod | J79: 119 | K79: 136 | L79: 153 | M79: 255 | N79: =G79&": ("&J79&", "&K79&", "&L79&", "&M79&", "&F79&": "&H79&")," -> 78: (119, 136, 153, 255, Net snow loss (amount) (snowmelt): 35123), | O79: =VLOOKUP(Australia!B79,Impacts!$A$2:$B$80,2, FALSE) -> Decrease in the quantity of snow | P79: =VLOOKUP(E79,Pressures!$A$2:$B$145,2,FALSE) -> Water produced by the melting of snow. | AC79: 228228 | AD79: 220220 | DU79: 1 | DY79: 1 | ET79: =SUM(DO79:ES79) -> 2
A80: 36 | B80: Net snow gain - extent | C80: snowfall | D80: 116 | E80: Snowfall | F80: Net snow gain (extent) (snowfall) | G80: 79 | H80: =(A80*1000)+D80 -> 36116 | I80: Gray | J80: 245 | K80: 245 | L80: 245 | M80: 255 | N80: =G80&": ("&J80&", "&K80&", "&L80&", "&M80&", "&F80&": "&H80&")," -> 79: (245, 245, 245, 255, Net snow gain (extent) (snowfall): 36116), | O80: =VLOOKUP(Australia!B80,Impacts!$A$2:$B$80,2, FALSE) -> Progressive gain of snow extent. | P80: =VLOOKUP(E80,Pressures!$A$2:$B$145,2,FALSE) -> Where water vapour turns into solid ice crystals and falls as snow. | AE80: 112228 | AF80: 123228 | AG80: 124228 | AH80: 215228 | AI80: 216228 | AJ80: 111220 | AK80: 112220 | AL80: 123220 | AM80: 124220 | AN80: 215220 | AO80: 216220 | DZ80: 1 | EB80: 1 | ET80: =SUM(DO80:ES80) -> 2
A81: 37 | B81: Net snow loss - extent | C81: snowmelt | D81: 117 | E81: Snowmelt | F81: Net snow loss (extent) (snowmelt) | G81: 80 | H81: =(A81*1000)+D81 -> 37117 | I81: Green Yellow | J81: 192 | K81: 192 | L81: 192 | M81: 255 | N81: =G81&": ("&J81&", "&K81&", "&L81&", "&M81&", "&F81&": "&H81&")," -> 80: (192, 192, 192, 255, Net snow loss (extent) (snowmelt): 37117), | O81: =VLOOKUP(Australia!B81,Impacts!$A$2:$B$80,2, FALSE) -> Loss of snow cover through melt resulting in exposure of the underlying surface. | P81: =VLOOKUP(E81,Pressures!$A$2:$B$145,2,FALSE) -> Water produced by the melting of snow. | AE81: 228112 | AF81: 228123 | AG81: 228124 | AH81: 228215 | AI81: 228216 | AJ81: 220111 | AK81: 220112 | AL81: 220123 | AM81: 220124 | AN81: 220215 | AO81: 220216 | DU81: 1 | DZ81: 1 | ET81: =SUM(DO81:ES81) -> 2
A82: 38 | B82: Net snow gain - hydroperiod | C82: prolonged temperature decrease | D82: 96 | E82: Prolonged temperature decrease | F82: Net snow gain (hydroperiod) (prolonged temperature decrease) | G82: 81 | H82: =(A82*1000)+D82 -> 38096 | I82: Honeydew | J82: 255 | K82: 250 | L82: 240 | M82: 255 | N82: =G82&": ("&J82&", "&K82&", "&L82&", "&M82&", "&F82&": "&H82&")," -> 81: (255, 250, 240, 255, Net snow gain (hydroperiod) (prolonged temperature decrease): 38096), | O82: =VLOOKUP(Australia!B82,Impacts!$A$2:$B$80,2, FALSE) -> The increase in the residence time of snow cover, often expressed as a percentage of a year. | P82: =VLOOKUP(E82,Pressures!$A$2:$B$145,2,FALSE) -> Seasonal to multi-annual decreases in temperature compared with past averages. | AC82: 228228 | AD82: 220220 | DA82: 98 | DB82: 97 | DC82: 91 | DD82: 87 | DE82: 81 | DF82: 71 | DY82: 1 | ET82: =SUM(DO82:ES82) -> 1
A83: 39 | B83: Net snow loss - hydroperiod | C83: prolonged temperature increase | D83: 97 | E83: Prolonged temperature increase | F83: Net snow loss (hydroperiod) (prolonged temperature increase) | G83: 82 | H83: =(A83*1000)+D83 -> 39097 | I83: Hot Pink | J83: 220 | K83: 220 | L83: 220 | M83: 255 | N83: =G83&": ("&J83&", "&K83&", "&L83&", "&M83&", "&F83&": "&H83&")," -> 82: (220, 220, 220, 255, Net snow loss (hydroperiod) (prolonged temperature increase): 39097), | O83: =VLOOKUP(Australia!B83,Impacts!$A$2:$B$80,2, FALSE) -> The decrease in the residence time of snow cover, often expressed as a percentage of a year. | P83: =VLOOKUP(E83,Pressures!$A$2:$B$145,2,FALSE) -> Seasonal to multi-annual increases in temperature compared with past averages. | AC83: 228228 | AD83: 220220 | AU83: 1 | AV83: 1 | AW83: 0 | AY83: 1 | AZ83: 2 | BA83: 3 | BJ83: 228228 | BK83: 220220 | BY83: 2 | CB83: 1012 | CC83: 1013 | CD83: 1015 | CE83: 1016 | CF83: 1213 | CG83: 1215 | CH83: 1216 | CI83: 1315 | CJ83: 1316 | CK83: 1516 | CL83: 1010 | CM83: 1212 | CN83: 1313 | CO83: 1515 | CP83: 1616 | CZ83: 2 | DA83: 17 | DB83: 18 | DC83: 19 | DD83: 78 | DE83: 79 | DF83: 89 | DY83: 1 | ET83: =SUM(DO83:ES83) -> 1
A84: 40 | B84: Phenological change | C84: natural diurnal and seasonal cycles | D84: 82 | E84: Natural diurnal and seasonal cycles | F84: Phenological change (natural diurnal and seasonal cycles) | G84: 83 | H84: =(A84*1000)+D84 -> 40082 | I84: Indigo | J84: 218 | K84: 165 | L84: 32 | M84: 255 | N84: =G84&": ("&J84&", "&K84&", "&L84&", "&M84&", "&F84&": "&H84&")," -> 83: (218, 165, 32, 255, Phenological change (natural diurnal and seasonal cycles): 40082), | O84: =VLOOKUP(Australia!B84,Impacts!$A$2:$B$80,2, FALSE) -> Alteration in the timing of natural lifecycle events. | P84: =VLOOKUP(E84,Pressures!$A$2:$B$145,2,FALSE) -> Changes in day length or temperatures over a year. | V84: 111111 | W84: 112112 | X84: 123123 | Y84: 124124 | AW84: 1 | AX84: 0 | AZ84: 1 | BA84: 2 | BB84: 3 | BK84: 228228 | BL84: 220220 | EI84: 1 | ET84: =SUM(DO84:ES84) -> 1
A85: 41 | B85: Railway or road abandonment | C85: reduced investment | D85: 98 | E85: Reduced investment | F85: Railway or road abandonment (reduced investment) | G85: 84 | H85: =(A85*1000)+D85 -> 41098 | I85: Ivory | J85: 75 | K85: 0 | L85: 130 | M85: 255 | N85: =G85&": ("&J85&", "&K85&", "&L85&", "&M85&", "&F85&": "&H85&")," -> 84: (75, 0, 130, 255, Railway or road abandonment (reduced investment): 41098), | O85: =VLOOKUP(Australia!B85,Impacts!$A$2:$B$80,2, FALSE) -> Transport infrastructure no longer in use and no new use observed. | P85: =VLOOKUP(E85,Pressures!$A$2:$B$145,2,FALSE) -> Sale of an asset or item or removing funding from a service. | Z85: 215215 | AW85: 1 | AX85: 0 | AZ85: 1 | BA85: 2 | BB85: 3 | BL85: 220220 | EL85: 1 | ET85: =SUM(DO85:ES85) -> 1
A86: 42 | B86: Railway or road construction | C86: increased investment | D86: 61 | E86: Increased investment | F86: Railway or road construction (increased investment) | G86: 85 | H86: =(A86*1000)+D86 -> 42061 | I86: Khaki | J86: 240 | K86: 128 | L86: 128 | M86: 255 | N86: =G86&": ("&J86&", "&K86&", "&L86&", "&M86&", "&F86&": "&H86&")," -> 85: (240, 128, 128, 255, Railway or road construction (increased investment): 42061), | O86: =VLOOKUP(Australia!B86,Impacts!$A$2:$B$80,2, FALSE) -> Building of a land cover that consists of a combination of materials to form a linear structure. | P86: =VLOOKUP(E86,Pressures!$A$2:$B$145,2,FALSE) -> Purchase of an asset, item or service. | Z86: 215215 | AE86: 111215 | AF86: 112215 | AG86: 123215 | AH86: 124215 | AI86: 216215 | AW86: 1 | AX86: 0 | AZ86: 1 | BA86: 2 | BB86: 3 | BD86: 111111 | BE86: 112112 | BF86: 123123 | BG86: 124124 | BH86: 215215 | BI86: 216216 | BV86: 22 | EL86: 1 | ET86: =SUM(DO86:ES86) -> 1
A87: 43 | B87: Receding flood | C87: reduced runoff post flood | D87: 100 | E87: Reduced runoff post flood | F87: Receding Flood (reduced runoff post flood) | G87: 86 | H87: =(A87*1000)+D87 -> 43100 | I87: Lavender Blush | J87: 255 | K87: 165 | L87: 0 | M87: 255 | N87: =G87&": ("&J87&", "&K87&", "&L87&", "&M87&", "&F87&": "&H87&")," -> 86: (255, 165, 0, 255, Receding Flood (reduced runoff post flood): 43100), | O87: =VLOOKUP(Australia!B87,Impacts!$A$2:$B$80,2, FALSE) -> Movement of water away from an area after a flood. | P87: =VLOOKUP(E87,Pressures!$A$2:$B$145,2,FALSE) -> Reduced quantity of water discharged in surface streams. | AE87: 228112 | AF87: 228123 | AG87: 228124 | AH87: 228215 | AI87: 228216 | AJ87: 220111 | AK87: 220112 | AL87: 220123 | AM87: 220124 | AN87: 220215 | AO87: 220216 | AW87: 1 | AX87: 0 | AZ87: 1 | BA87: 2 | BB87: 3 | BL87: 220220 | DS87: 1 | DT87: 1 | ET87: =SUM(DO87:ES87) -> 2
A88: 44 | B88: Salinisation | C88: evaporation | D88: 37 | E88: Evaporation | F88: Salinisation (evaporation) | G88: 87 | H88: =(A88*1000)+D88 -> 44037 | I88: Lawn Green | J88: 221 | K88: 160 | L88: 221 | M88: 255 | N88: =G88&": ("&J88&", "&K88&", "&L88&", "&M88&", "&F88&": "&H88&")," -> 87: (221, 160, 221, 255, Salinisation (evaporation): 44037), | O88: =VLOOKUP(Australia!B88,Impacts!$A$2:$B$80,2, FALSE) -> The process of soils becoming more salty. | P88: =VLOOKUP(E88,Pressures!$A$2:$B$145,2,FALSE) -> Water changing from a liquid to a gas. | AB88: 227227 | AC88: 228228 | AD88: 220220 | AW88: 1 | AX88: 0 | AZ88: 1 | BA88: 2 | BB88: 3 | BL88: 220220 | CZ88: 11 | DZ88: 1 | EB88: 1 | ET88: =SUM(DO88:ES88) -> 2
A89: 44 | B89: Salinisation | C89: sea level fluctuation | D89: 110 | E89: Sea level fluctuation | F89: Salinisation (sea level fluctuation) | G89: 88 | H89: =(A89*1000)+D89 -> 44110 | I89: Lemon Chiffon | J89: 238 | K89: 130 | L89: 238 | M89: 255 | N89: =G89&": ("&J89&", "&K89&", "&L89&", "&M89&", "&F89&": "&H89&")," -> 88: (238, 130, 238, 255, Salinisation (sea level fluctuation): 44110), | O89: =VLOOKUP(Australia!B89,Impacts!$A$2:$B$80,2, FALSE) -> The process of soils becoming more salty. | P89: =VLOOKUP(E89,Pressures!$A$2:$B$145,2,FALSE) -> Irregular rise and fall of sea level. | AC89: 228228 | AD89: 220220 | AW89: 1 | AX89: 0 | AZ89: 1 | BA89: 2 | BB89: 3 | BH89: 215216 | EE89: 1 | ET89: =SUM(DO89:ES89) -> 1
A90: 45 | B90: Sea ice decrease | C90: prolonged temperature increase | D90: 97 | E90: Prolonged temperature increase | F90: Sea ice decrease (prolonged temperature increase) | G90: 89 | H90: =(A90*1000)+D90 -> 45097 | I90: Light Blue | J90: 176 | K90: 196 | L90: 222 | M90: 255 | N90: =G90&": ("&J90&", "&K90&", "&L90&", "&M90&", "&F90&": "&H90&")," -> 89: (176, 196, 222, 255, Sea ice decrease (prolonged temperature increase): 45097), | O90: =VLOOKUP(Australia!B90,Impacts!$A$2:$B$80,2, FALSE) -> Decrease in the extent and/or volume of frozen marine water. | P90: =VLOOKUP(E90,Pressures!$A$2:$B$145,2,FALSE) -> Seasonal to multi-annual increases in temperature compared with past averages. | AC90: 228228 | AD90: 220220 | AW90: 1 | AX90: 0 | AZ90: 1 | BA90: 2 | BB90: 3 | BH90: 215220 | CZ90: 31 | DA90: 17 | DB90: 18 | DC90: 19 | DD90: 78 | DE90: 79 | DF90: 89 | DX90: 1 | DY90: 1 | ET90: =SUM(DO90:ES90) -> 2
A91: 46 | B91: Sea ice increase | C91: prolonged temperature decrease | D91: 96 | E91: Prolonged temperature decrease | F91: Sea ice increase (prolonged temperature decrease) | G91: 90 | H91: =(A91*1000)+D91 -> 46096 | I91: Light Coral | J91: 255 | K91: 255 | L91: 255 | M91: 255 | N91: =G91&": ("&J91&", "&K91&", "&L91&", "&M91&", "&F91&": "&H91&")," -> 90: (255, 255, 255, 255, Sea ice increase (prolonged temperature decrease): 46096), | O91: =VLOOKUP(Australia!B91,Impacts!$A$2:$B$80,2, FALSE) -> Increae in the extent and/or volume of frozen marine water. | P91: =VLOOKUP(E91,Pressures!$A$2:$B$145,2,FALSE) -> Seasonal to multi-annual decreases in temperature compared with past averages. | AC91: 228228 | AD91: 220220 | AW91: 1 | AX91: 0 | AZ91: 1 | BA91: 2 | BB91: 3 | BH91: 215216 | CZ91: 13 | DA91: 98 | DB91: 97 | DC91: 91 | DD91: 87 | DE91: 81 | DF91: 71 | DX91: 1 | DY91: 1 | ET91: =SUM(DO91:ES91) -> 2
A92: 47 | B92: Sea level fall | C92: ocean-atmosphere oscillations | D92: 85 | E92: Ocean-atmosphere oscillations | F92: Sea level fall (ocean-atmosphere oscillations) | G92: 91 | H92: =(A92*1000)+D92 -> 47085 | I92: Light Goldenrod Yellow | J92: 0 | K92: 139 | L92: 139 | M92: 255 | N92: =G92&": ("&J92&", "&K92&", "&L92&", "&M92&", "&F92&": "&H92&")," -> 91: (0, 139, 139, 255, Sea level fall (ocean-atmosphere oscillations): 47085), | O92: =VLOOKUP(Australia!B92,Impacts!$A$2:$B$80,2, FALSE) -> An decrease in the mean level of the oceans. | P92: =VLOOKUP(E92,Pressures!$A$2:$B$145,2,FALSE) -> Naturally occurring cycles affecting sea surface temperature and precipitation | AE92: 228112 | AF92: 228124 | AG92: 228216 | AH92: 220112 | AI92: 220124 | AJ92: 220216 | AW92: 1 | AX92: 0 | AZ92: 1 | BA92: 2 | BB92: 3 | BH92: 215215 | EA92: 1 | ET92: =SUM(DO92:ES92) -> 1
A93: 48 | B93: Sea level rise | C93: melting ice sheets/glaciers | D93: 76 | E93: Melting ice sheets/glaciers | F93: Sea level rise (melting ice sheets/glaciers) | G93: 92 | H93: =(A93*1000)+D93 -> 48076 | I93: Light Gray | J93: 0 | K93: 191 | L93: 255 | M93: 255 | N93: =G93&": ("&J93&", "&K93&", "&L93&", "&M93&", "&F93&": "&H93&")," -> 92: (0, 191, 255, 255, Sea level rise (melting ice sheets/glaciers): 48076), | O93: =VLOOKUP(Australia!B93,Impacts!$A$2:$B$80,2, FALSE) -> An increase in the mean level of the oceans. | P93: =VLOOKUP(E93,Pressures!$A$2:$B$145,2,FALSE) -> Loss in the extent and volume of frozen water floating on or within sea water. | AW93: 1 | AX93: 0 | AZ93: 1 | BA93: 2 | BB93: 3 | BH93: 215215 | DU93: 1 | ET93: =SUM(DO93:ES93) -> 1
A94: 48 | B94: Sea level rise | C94: thermal expansion | D94: 124 | E94: Thermal expansion | F94: Sea level rise (thermal expansion) | G94: 93 | H94: =(A94*1000)+D94 -> 48124 | I94: Light Pink | J94: 32 | K94: 178 | L94: 170 | M94: 255 | N94: =G94&": ("&J94&", "&K94&", "&L94&", "&M94&", "&F94&": "&H94&")," -> 93: (32, 178, 170, 255, Sea level rise (thermal expansion): 48124), | O94: =VLOOKUP(Australia!B94,Impacts!$A$2:$B$80,2, FALSE) -> An increase in the mean level of the oceans. | P94: =VLOOKUP(E94,Pressures!$A$2:$B$145,2,FALSE) -> Increase in linear dimensions of a solid or in volume of a fluid because of rise in temperature. | AE94: 112228 | AF94: 123228 | AG94: 124228 | AH94: 215228 | AI94: 216228 | AJ94: 111220 | AK94: 112220 | AL94: 123220 | AM94: 124220 | AN94: 215220 | AO94: 216220 | AW94: 1 | AX94: 0 | AZ94: 1 | BA94: 2 | BB94: 3 | BH94: 215215 | DS94: 1 | DX94: 1 | ET94: =SUM(DO94:ES94) -> 2
A95: 49 | B95: Sedimentation | C95: dredging | D95: 29 | E95: Dredging | F95: Sedimentation (dredging) | G95: 94 | H95: =(A95*1000)+D95 -> 49029 | I95: Light Salmon | J95: 233 | K95: 150 | L95: 122 | M95: 255 | N95: =G95&": ("&J95&", "&K95&", "&L95&", "&M95&", "&F95&": "&H95&")," -> 94: (233, 150, 122, 255, Sedimentation (dredging): 49029), | O95: =VLOOKUP(Australia!B95,Impacts!$A$2:$B$80,2, FALSE) -> Deposition of sediment from flowing or standing water | P95: =VLOOKUP(E95,Pressures!$A$2:$B$145,2,FALSE) -> Removing silt and other material from the bottom of bodies of water | AC95: 228228 | AD95: 220220 | AW95: 1 | AX95: 0 | AZ95: 1 | BA95: 2 | BB95: 3 | BH95: 215215 | DR95: 1 | DV95: 1 | EK95: 1 | ET95: =SUM(DO95:ES95) -> 3
A96: 50 | B96: Sinkhole | C96: subsidence | D96: 122 | E96: Subsidence | F96: Sink hole (subsidence) | G96: 95 | H96: =(A96*1000)+D96 -> 50122 | I96: Light Sea Green | J96: 240 | K96: 255 | L96: 240 | M96: 255 | N96: =G96&": ("&J96&", "&K96&", "&L96&", "&M96&", "&F96&": "&H96&")," -> 95: (240, 255, 240, 255, Sink hole (subsidence): 50122), | O96: =VLOOKUP(Australia!B96,Impacts!$A$2:$B$80,2, FALSE) -> A closed natural depression in the ground surface. | P96: =VLOOKUP(E96,Pressures!$A$2:$B$145,2,FALSE) -> The lowering of the Earth's surface, caused by factors such as compaction, a decrease in ground water or earthquakes. | V96: 111111 | W96: 112112 | X96: 123123 | Y96: 124124 | Z96: 215215 | AA96: 216216 | AB96: 227227 | AC96: 228228 | AD96: 220220 | AW96: 1 | AX96: 0 | AZ96: 1 | BA96: 2 | BB96: 3 | BH96: 215215 | EF96: 1 | ET96: =SUM(DO96:ES96) -> 1
A97: 51 | B97: Snow accumulation | C97: snowfall | D97: 116 | E97: Snowfall | F97: Snow accumulation (snowfall) | G97: 96 | H97: =(A97*1000)+D97 -> 51116 | I97: Light Slate Gray | J97: 240 | K97: 248 | L97: 255 | M97: 255 | N97: =G97&": ("&J97&", "&K97&", "&L97&", "&M97&", "&F97&": "&H97&")," -> 96: (240, 248, 255, 255, Snow accumulation (snowfall): 51116), | O97: =VLOOKUP(Australia!B97,Impacts!$A$2:$B$80,2, FALSE) -> Gradual gathering of snow over an area already covered in snow. | P97: =VLOOKUP(E97,Pressures!$A$2:$B$145,2,FALSE) -> Where water vapour turns into solid ice crystals and falls as snow. | AE97: 112228 | AF97: 123228 | AG97: 124228 | AH97: 215228 | AI97: 216228 | AJ97: 111220 | AK97: 112220 | AL97: 123220 | AM97: 124220 | AN97: 215220 | AO97: 216220 | AW97: 1 | AX97: 0 | AZ97: 1 | BA97: 2 | BB97: 3 | BH97: 215215 | CZ97: 22 | DU97: 1 | EA97: 1 | EB97: 1 | ET97: =SUM(DO97:ES97) -> 3
A98: 52 | B98: Snow melt | C98: increased temperature | D98: 64 | E98: Increased temperature | F98: Snow melt (increased temperature) | G98: 97 | H98: =(A98*1000)+D98 -> 52064 | I98: Light Steel Blue | J98: 169 | K98: 169 | L98: 169 | M98: 255 | N98: =G98&": ("&J98&", "&K98&", "&L98&", "&M98&", "&F98&": "&H98&")," -> 97: (169, 169, 169, 255, Snow melt (increased temperature): 52064), | O98: =VLOOKUP(Australia!B98,Impacts!$A$2:$B$80,2, FALSE) -> Loss of snow cover due to heat. | P98: =VLOOKUP(E98,Pressures!$A$2:$B$145,2,FALSE) -> Increased amount of heat in a place. | AE98: 228112 | AF98: 228123 | AG98: 228124 | AH98: 228215 | AI98: 228216 | AJ98: 220111 | AK98: 220112 | AL98: 220123 | AM98: 220124 | AN98: 220215 | AO98: 220216 | AW98: 1 | AX98: 0 | AZ98: 1 | BA98: 2 | BB98: 3 | BH98: 215215 | CZ98: 21 | DY98: 1 | ET98: =SUM(DO98:ES98) -> 1
A99: 53 | B99: Urban area loss | C99: earthquake | D99: 32 | E99: Earthquake | F99: Urban area loss (earthquake) | G99: 98 | H99: =(A99*1000)+D99 -> 53032 | I99: Light Yellow | J99: 199 | K99: 21 | L99: 133 | M99: 255 | N99: =G99&": ("&J99&", "&K99&", "&L99&", "&M99&", "&F99&": "&H99&")," -> 98: (199, 21, 133, 255, Urban area loss (earthquake): 53032), | O99: =VLOOKUP(Australia!B99,Impacts!$A$2:$B$80,2, FALSE) -> Removal of all settlements above a certain minimum population size and density. | P99: =VLOOKUP(E99,Pressures!$A$2:$B$145,2,FALSE) -> The vibrations of the Earth caused by the passage of seismic waves radiating from some source of elastic energy. | AE99: 215216 | AW99: 0 | AX99: 0 | AZ99: 1 | BA99: 2 | BB99: 3 | BD99: 111111 | BE99: 112112 | BF99: 123123 | BG99: 124124 | BV99: 22 | BY99: -□ | EF99: 1 | ET99: =SUM(DO99:ES99) -> 1
A100: 53 | B100: Urban area loss | C100: flooding | D100: 44 | E100: Flooding | F100: Urban area loss (flooding) | G100: 99 | H100: =(A100*1000)+D100 -> 53044 | I100: Lime | J100: 90 | K100: 79 | L100: 207 | M100: 255 | N100: =G100&": ("&J100&", "&K100&", "&L100&", "&M100&", "&F100&": "&H100&")," -> 99: (90, 79, 207, 255, Urban area loss (flooding): 53044), | O100: =VLOOKUP(Australia!B100,Impacts!$A$2:$B$80,2, FALSE) -> Removal of all settlements above a certain minimum population size and density. | P100: =VLOOKUP(E100,Pressures!$A$2:$B$145,2,FALSE) -> The inundation of water over land that is generally dry. | AE100: 215228 | AF100: 215220 | AW100: 0 | AX100: 0 | AZ100: 1 | BA100: 2 | BB100: 3 | BD100: 111111 | BE100: 112112 | BF100: 123123 | BG100: 124124 | BV100: 22 | BY100: - | DS100: 1 | ET100: =SUM(DO100:ES100) -> 1
...

Sheet colours
A1: ID_Colour | B1: R | C1: G | D1: B | E1: Colour | F1: A | G1: Code
A2: Medium Slate Blue | B2: 123 | C2: 104 | D2: 238 | F2: 255 | G2: 1113: (123, 104, 238, 255, Accretion (sediment transport)),
A3: Light Slate Gray | B3: 119 | C3: 136 | D3: 153 | F3: 255 | G3: 2038: (119, 136, 153, 255, Algal bloom (eutrophication)),
A4: Medium Orchid | B4: 186 | C4: 85 | D4: 211 | F4: 255 | G4: 2060: (186, 85, 211, 255, Algal bloom (high inland water temperatures)),
A5: Light Salmon | B5: 255 | C5: 160 | D5: 122 | F5: 255 | G5: 2068: (255, 160, 122, 255, Algal bloom (increased temperature)),
A6: Dark Turquoise | B6: 0 | C6: 206 | D6: 209 | F6: 255 | G6: 3027: (0, 206, 209, 255, Algal dieback (decreased temperature)),
A7: Light Sky Blue | B7: 135 | C7: 206 | D7: 250 | F7: 255 | G7: 4012: (135, 206, 250, 255, Bare soil exposure (burning)),
A8: Light Steel Blue | B8: 176 | C8: 196 | D8: 222 | F8: 255 | G8: 4037: (176, 196, 222, 255, Bare soil exposure (erosion)),
A9: Medium Purple | B9: 147 | C9: 112 | D9: 219 | F9: 255 | G9: 4093: (147, 112, 219, 255, Bare soil exposure (ploughing)),
A10: Pale Violet Red | B10: 219 | C10: 112 | D10: 147 | F10: 255 | G10: 4127: (219, 112, 147, 255, Bare soil exposure (tillage)),
A11: Light Green | B11: 144 | C11: 238 | D11: 144 | F11: 255 | G11: 5072: (144, 238, 144, 255, Blackwater event (inundation following extended drought)),
A12: Medium Spring Green | B12: 0 | C12: 250 | D12: 154 | F12: 255 | G12: 6026: (0, 250, 154, 255, Browning (vegetation) (decreased precipitation)),
A13: Light Cyan | B13: 224 | C13: 255 | D13: 255 | F13: 255 | G13: 7022: (224, 255, 255, 255, Building or infrastructure abandonment (dam removal)),
... A247: Pear | B247: 209 | C247: 226 | D247: 49 | F247: 255 | G247: 75094: (209, 226, 49, 255, Water quality change (pollution)),
A248: Teal Blue | B248: 54 | C248: 117 | D248: 136 | G248: : (54, 117, 136, , ),
A249: Neon Green | B249: 57 | C249: 255 | D249: 20 | G249: : (57, 255, 20, , ),
A250: Neon Fuchsia | B250: 254 | C250: 65 | D250: 100 | G250: : (254, 65, 100, , ),
A251: Dark Brown | B251: 101 | C251: 67 | D251: 33 | G251: : (101, 67, 33, , ),
A252: Khaki Web | B252: 195 | C252: 176 | D252: 145 | G252: : (195, 176, 145, , ),
A253: Iceberg | B253: 113 | C253: 166 | D253: 210 | G253: : (113, 166, 210, , ),
A254: Jasmine | B254: 248 | C254: 222 | D254: 126 | G254: : (248, 222, 126, , ),
A255: Mahogany | B255: 192 | C255: 64 | D255: 0 | G255: : (192, 64, 0, , ),
A256: French Rose | B256: 246 | C256: 74 | D256: 138 | G256: : (246, 74, 138, , ),
A257: Cyan-Blue Azure | B257: 70 | C257: 130 | D257: 191 | G257: : (70, 130, 191, , ),
A258: Fuchsia | B258: 255 | C258: 0 | D258: 255 | G258: : (255, 0, 255, , ),

Sheet Impacts
A1: Term | B1: Definition short | C1: Definition | E1: Copyright | F1: Authority | G1: Authority citation | H1: Authority link
A2: Accretion | B2: The build-up of sediments to form land or shoaling in coastal waters or waterways. | C2: The build-up of sediments to form land or shoaling in coastal waters or waterways. It may be either natural or artificial. Natural accretion is the build-up of land on the beach, dunes, or in the water by natural processes, such as waves, current and wind. Artificial accretion is a similar build-up of land resulting from built structures such as groynes or breakwaters, or activities such as filling and beach nourishment, or also aggradation. | E2: The definition for this term is re-used from 'Costal Management Glossary', Office of Environment and Heritage © 2018 State of NSW and Office of Environment and Heritage. It is licensed under the Creative Commons Attribution 4.0 International (CC BY 4.0). | F2: Office of Environment and Heritage | G2: OEH 2018. Coastal Management Glossary. <last accessed 14th Dec 2020 https://www.environment.nsw.gov.au/research-and-publications/publications-search/coastal-management-glossary> | H2: https://www.environment.nsw.gov.au/-/media/OEH/Corporate-Site/Documents/Water/Coasts/coastal-management-glossary-180195.pdf
A3: Algal bloom | B3: A sudden proliferation of algae (microscopic plants) that occurs near the surface of a body of water. | C3: A sudden proliferation of algae (microscopic plants) that occurs near the surface of a body of water. Blooms can occur due to natural nutrient cycles, or can be in response to eutrophication or climate variations. | E3: The definition for this term is re-used from Australia State of the Environment 2016 Glossary, © Commonwealth of Australia 2017-2018. It is licenced by the Commonwealth of Australia for use under a Creative Commons Attribution 4.0 International licence. | F3: Australia State of the Environment 2016 | G3: - | H3: https://soe.environment.gov.au/glossary
A4: Algal dieback | B4: Loss of algae (microscopic plants) that occurs near the surface of a body of water. | C4: Loss of algae (microscopic plants) that occurs near the surface of a body of water. | E4: Part of the definition for this term is re-used from Australia State of the Environment 2016 Glossary, © Commonwealth of Australia 2017-2018. It is licenced by the Commonwealth of Australia for use under a Creative Commons Attribution 4.0 International licence. | F4: Australia State of the Environment 2016 | G4: - | H4: https://soe.environment.gov.au/glossary
A5: Bare soil exposure | B5: Appearance of underlying soil following human or natural disturbance.. | C5: Appearance of underlying soil following human or natural disturbance, such as removal of top soil prior to urban construction or grazing of natural vegetation. | E5: Creative Commons Attribution 4.0 International (CC BY 4.0) license, on any reports made public under this Project Agreement. | F5: Land Ecosystem Accounts Project | G5: - | H5: General - no source
A6: Blackwater event | B6: When organic material is inundated or washed into waterways and consumed by bacteria. | C6: When organic material is inundated or washed into waterways and consumed by bacteria, leading to a sudden depletion of dissolved oxygen in the water. | E6: The definition for this term is re-used from Australia State of the Environment 2016 Glossary, © Commonwealth of Australia 2017-2018. It is licenced by the Commonwealth of Australia for use under a Creative Commons Attribution 4.0 International licence. | F6: Australia State of the Environment 2016 | G6: - | H6: https://soe.environment.gov.au/glossary
A7: Browning (vegetation) | B7: A decrease in the amount or loss of photosynthetically active pigments in vegetation. | C7: A decrease in the amount or loss of photosynthetically active pigments (primarily chlorophylls) in vegetation. | E7: Creative Commons Attribution 4.0 International (CC BY 4.0) license, on any reports made public under this Project Agreement. | F7: Land Ecosystem Accounts Project | G7: - | H7: General - no source
A8: Building or infrastucture abandonment | B8: Buildings dehabited or no longer in use. | C8: Buildings dehabited or no longer in use. | E8: Creative Commons Attribution 4.0 International (CC BY 4.0) license, on any reports made public under this Project Agreement. | F8: Land Ecosystem Accounts Project | G8: - | H8: General - no source
A9: Compaction | B9: Process that brings about an increase in soil density or unit weight. | C9: Process that brings about an increase in soil density or unit weight, accompanied by a decrease in air volume. | E9: The definition for this term is re-used from 'Compaction', University of West England, Copyright 2020 © UWE Bristol | F9: University of New England | G9: - | H9: http://environment.uwe.ac.uk/geocal/SoilMech/compaction/compaction.htm
A10: Coral bleaching | B10: When the coral host expels its zooxanthellae. | C10: When the coral host expels its zooxanthellae (marine algae living in symbiosis with the coral) in response to increased water temperatures, often resulting in the death of the coral. | E10: Part of the definition for this term is re-used from Australia State of the Environment 2016 Glossary, © Commonwealth of Australia 2017-2018. It is licenced by the Commonwealth of Australia for use under a Creative Commons Attribution 4.0 International licence. | F10: Australia State of the Environment 2016 | G10: - | H10: https://soe.environment.gov.au/glossary
A11: Coral damage | B11: Physical damage or loss of a coral reef not caused b y changes in water temperature | C11: Physical damage or loss of a coral reef that is not the result of changes in water. temperature. | E11: Creative Commons Attribution 4.0 International (CC BY 4.0) license, on any reports made public under this Project Agreement. | F11: Land Ecosystem Accounts Project | G11: - | H11: General - no source
A12: Coral recovery | B12: Re-instatement of the previous extent or health of reef-building corals. | C12: Re-instatement of the previous extent or health of reef-building corals. | E12: Creative Commons Attribution 4.0 International (CC BY 4.0) license, on any reports made public under this Project Agreement. | F12: Land Ecosystem Accounts Project | G12: - | H12: General - no source
... A19: Desalinisation | B19: The process of soils becoming less salty. | C19: The process of soils becoming less salty; the reduction of soluble salts in water bodies. | E19: Part of the definition for this term is re-used from Australia State of the Environment 2016 Glossary, © Commonwealth of Australia 2017-2018. It is licenced by the Commonwealth of Australia for use under a Creative Commons Attribution 4.0 International licence. | F19: Australia State of the Environment 2016 | G19: - | H19: https://soe.environment.gov.au/glossary
A20: Desertification | B20: Reduction in the productivity of the land that is not reversible. | C20: Reduction in the productivity of the land that is not reversible. In other words, land is desertified when it can no longer support the same plant growth it had in the past, and the change is permanent on a human time scale. | E20: Part of the definition for this term is re-used from 'Defining Desertification', NASA Earth Observatory. No specific copyright info (only this: https://www.nasa.gov/multimedia/guidelines/index.html) | F20: NASA Earth Observatory | H20: https://earthobservatory.nasa.gov/features/Desertification/desertification2.php
A21: Elevation change | B21: Change in the altitude above sea or ground level. | C21: Change in the altitude above sea or ground level. | E21: Part of the definition for this term is re-used from 'Elevation', Macquarie Dictionary. © Macmillan Publishers Australia 2020. All rights reserved. | F21: Macquarie Dictionary | G21: - | H21: https://www.macquariedictionary.com.au/features/word/search/?search_word_type=Dictionary&word=elevation
A22: Erosion | B22: Geological process in which earthen materials are worn away and transported by natural forces. | C22: Geological process in which earthen materials are worn away and transported by natural forces such as wind or water. | E22: The definition for this term is re-used from 'Erosion', National Geographic. © 1996 - 2020 National Geographic Society. All rights reserved. | F22: National Geographic | G22: - | H22: https://www.nationalgeographic.org/encyclopedia/erosion/#:~:text=Erosion%20is%20the%20geological%20process,such%20as%20wind%20or%20water.
A23: Flooding | B23: Inundation of water over an area. | C23: Inundation of water over an area. | E23: Creative Commons Attribution 4.0 International (CC BY 4.0) license, on any reports made public under this Project Agreement. | F23: Land Ecosystem Accounts Project | G23: - | H23: General - no source
A24: Geomorphological change | B24: A geomorphic adjustment that changes the geometry of landforms. | C24: A geomorphic adjustment that changes the geometry of landforms. Examples include estuarine evolution and beach rotation in coastal areas and mountain uplift. | E24: Creative Commons Attribution 4.0 International (CC BY 4.0) license, on any reports made public under this Project Agreement. | F24: Land Ecosystem Accounts Project | G24: - | H24: General - no source
A25: Glaciation | B25: Expansion of ice or glacier cover. | C25: Expansion of ice or glacier cover. | E25: Creative Commons Attribution 4.0 International (CC BY 4.0) license, on any reports made public under this Project Agreement. | F25: Land Ecosystem Accounts Project | G25: - | H25: General - no source
A26: Greening | B26: An increase in the amount of photosynthetically active pigments in vegetation. | C26: An increase in the amount of photosynthetically active pigments (primarily chlorophylls) in vegetation. | E26: Creative Commons Attribution 4.0 International (CC BY 4.0) license, on any reports made public under this Project Agreement. | F26: Land Ecosystem Accounts Project | G26: - | H26: General - no source
A27: Increased sediment load | B27: Increase in the amount of a substance discharged into a body of water. | C27: Increase in the amount of a substance discharged into a body of water (e.g. salt or sediment). | E27: Part of the definition for this term is re-used from 'Glossary', Northern Territory Environment Protection Authority,© Copyright 2020 NTEPA | F27: Northern Territory Environment Protection Authority | G27: NTEPA 2005, Glossary, Enesar Consulting Pty Ltd, NTEPA | H27: https://ntepa.nt.gov.au/__data/assets/pdf_file/0007/286567/chp12.pdf
A28: Inundation | B28: Progressive submergence of land or structures through flooding. | C28: Progressive submergence of land or structures through flooding. | E28: Creative Commons Attribution 4.0 International (CC BY 4.0) license, on any reports made public under this Project Agreement. | F28: New South Wales State Emergency Service | G28: SES 2018, New South Wales State Flood Plan Glossary, Page 3, [https://www.ses.nsw.gov.au/about-us/flood-storm-and-tsunami-plans/][last accessed 10th Dec 2020] | H28: https://www.ses.nsw.gov.au/media/2650/glossary.pdf
A29: Invasive or exotic species | B29: A plant or animal that has been introduced into a region (terrestrial or aquatic). | C29: A plant or animal that has been introduced into a region (terrestrial or aquatic) in which it does not naturally occur and that becomes established and spreads, displacing naturally occurring species. | E29: Creative Commons Attribution 4.0 International (CC BY 4.0) license, on any reports made public under this Project Agreement. | F29: Land Ecosystem Accounts Project | G29: - | H29: General - no source
A30: Lava flow | B30: A mass of molten rock produced during the eruption of a volcano and moving down its sides. | C30: A mass of molten rock produced during the eruption of a volcano and moving down its sides. | E30: The definition for this term is re-used from 'Lava flow', Macquarie Dictionary. © Macmillan Publishers Australia 2020. All rights reserved. | F30: Macquarie Dictionary | G30: - | H30: https://www.macquariedictionary.com.au/features/word/search/?search_word_type=Dictionary&word=lava+flow
A31: Leaf scorch | B31: A non-infectious, physiological condition caused by unfavorable environmental situations. | C31: A non-infectious, physiological condition caused by unfavorable environmental situations. It is not caused by fungus, bacteria, or virus. The problem may appear on almost any plant if weather conditions are favourable, such as high temperatures, dry winds, salt carrying winds and low soil moisture. | E31: The definition for this term is re-used from 'Leaf scorch', The Morton Arboretum, © 2021 The Morton Arboretum | F31: The Morton Arboretum | G31: - | H31: https://mortonarb.org/plant-and-protect/tree-plant-care/plant-care-resources/leaf-scorch/#!
A32: Mine abandonment | B32: Land formally used for extractive industry but no longer in use and no new use observed. | C32: Land formally used for extractive industry but no longer in use and no new use observed. | E32: Creative Commons Attribution 4.0 International (CC BY 4.0) license, on any reports made public under this Project Agreement. | F32: Land Ecosystem Accounts Project | G32: - | H32: General - no source
... A52: Sedimentation | B52: Deposition of sediment from flowing or standing water | C52: Deposition of sediment from flowing water (in channels or floodplains) or standing water (in wetlands, lakes, or oceans). | E52: The definition for this term is re-used from ' Soil erosion: the greatest challenge to sustainable soil management', Food and Agriculture Organisation; © FAO, 2019. Some rights reserved. This work is made available under the Creative Commons AttributionNonCommercial-ShareAlike 3.0 IGO licence | F52: Food and Agriculture Organisation of the United Nations | G52: FAO. 2019. Soil erosion: the greatest challenge to sustainable soil management. Rome. 100 pp. Licence: CC BY-NC-SA 3.0 IGO. http://www.fao.org/3/ca4395en/ca4395en.pdf | H52: http://www.fao.org/3/ca4395en/ca4395en.pdf
A53: Sinkhole | B53: A closed natural depression in the ground surface. | C53: A sinkhole is a closed natural depression in the ground surface caused by removal of material below the ground and either collapse or gradual subsidence of the surface into the resulting void. | E53: The definition for this term is re-used from 'What is the difference between a sinkhole and a pothole?', USGS. Generally, materials produced by federal agencies are in the public domain and may be reproduced without permission. | F53: United States Geological Survey | H53: https://www.usgs.gov/faqs/what-difference-between-a-sinkhole-and-a-pothole?qt-news_science_products=0#qt-news_science_products
A54: Snow accumulation | B54: Gradual gathering of snow over an area already covered in snow. | C54: Gradual gathering of snow over an area already covered in snow. | E54: Creative Commons Attribution 4.0 International (CC BY 4.0) license, on any reports made public under this Project Agreement. | F54: Land Ecosystem Accounts Project | G54: - | H54: General - no source
A55: Snow melt | B55: Loss of snow cover due to heat. | C55: Loss of snow cover due to heat. | E55: Creative Commons Attribution 4.0 International (CC BY 4.0) license, on any reports made public under this Project Agreement. | F55: Land Ecosystem Accounts Project | G55: - | H55: General - no source
A56: Urban damage | B56: Damage to urban buildings and infrastructure. | C56: Damage to urban buildings and infrastructure. | E56: Creative Commons Attribution 4.0 International (CC BY 4.0) license, on any reports made public under this Project Agreement. | F56: Land Ecosystem Accounts Project | G56: - | H56: General - no source
A57: Urban decay | B57: The process of deterioration in the integrity of buildings and infrastructure. | C57: The process of deterioration in the integrity of buildings and infrastructure. | E57: Part of the definition for this term is re-used from 'Dictionary of Geographical Terms', © 2007 - 2020 Collins Learning, a division of HarperCollins Publishers Ltd, registered in Scotland, Company No.27389. Registered address: Westerhill Road, Bishopbriggs, Glasgow, G64 2QT. © 2020 National Geographic Partners, LLC. | F57: Collins Dictionary | G57: - | H57: https://resources.collins.co.uk/Wesbite%20images/KS3Geography/TB2/Dictionary%20of%20geographical%20terms.pdf
A58: Urban densification | B58: Increases in the number of buildings and associated infrastructure. | C58: Increases in the number of buildings and associated infrastructure as human populations move into an area to live or work. | E58: Creative Commons Attribution 4.0 International (CC BY 4.0) license, on any reports made public under this Project Agreement. | F58: Land Ecosystem Accounts Project | G58: - | H58: General - no source
A59: Urban development | B59: Economic, social and political changes that improve the wellbeing of people in an urban setting. | C59: Economic, social and political changes that improve the wellbeing of people in an urban setting. | E59: Part of the definition for this term is re-used from 'Glossary', Australian Curriculum, © Australian Curriculum, Assessment and Reporting Authority. | F59: Australian Curriculum | G59: - | H59: https://www.australiancurriculum.edu.au/f-10-curriculum/humanities-and-social-sciences/geography/glossary/?letter=D
A60: Urban growth | B60: Increase urban area through the construction of buildings and associated infrastructure. | C60: Increase in extent of urban land cover through the construction of buildings and associated infrastructure. | E60: Creative Commons Attribution 4.0 International (CC BY 4.0) license, on any reports made public under this Project Agreement. | F60: Land Ecosystem Accounts Project | G60: - | H60: General - no source
A61: Urban area loss | B61: Removal of all settlements above a certain minimum population size and density. | C61: Removal of all settlements above a certain minimum population size and minimum population density that are within a certain travel time by road. | E61: Part of the definition for this term is re-used from © 2009 The International Bank for Reconstruction and Development/The World Bank | F61: World Bank World Development Report 2009 | G61: - | H61: http://www-wds.worldbank.org/external/default/WDSContentServer/WDSP/IB/2008/12/03/000333038_20081203234958/Rendered/PDF/437380REVISED01BLIC1097808213760720.pdf
A62: Urban renewal | B62: Redevelopment of a built environment to address urban decay. | C62: Redevelopment of a built environment to address urban decay. | E62: Creative Commons Attribution 4.0 International (CC BY 4.0) license, on any reports made public under this Project Agreement. | F62: Land Ecosystem Accounts Project | G62: - | H62: General - no source
A63: Urban sprawl | B63: Unplanned low-density development surrounding an urban area. | C63: Unplanned low-density development surrounding an urban area that often starts as rural land. Also called suburban sprawl. | E63: The definition for this term is re-used from 'Glossary', National Geographic. © 1996 - 2020 National Geographic Society. All rights reserved. | F63: National Geographic | G63: - | H63: https://www.nationalgeographic.org/glossary/?page=3&term=urban
A64: Vegetation damage | B64: Physical harm that impairs the value, usefulness, or normal function of plants or plant communities. | C64: Physical harm that impairs the value, usefulness, or normal function of plants or plant communities. | E64: Part of the definition for this term is re-used from 'Damage', Lexico, powered by Oxford © 2021 Lexico.com | F64: Lexico | G64: - | H64: https://www.lexico.com/definition/damage
A65: Vegetation dieback | B65: Mortality of all or part of plant components, either sinularly or en masse. | C65: Mortality of all or part of plant components, either sinularly or en masse. | E65: Creative Commons Attribution 4.0 International (CC BY 4.0) license, on any reports made public under this Project Agreement. | F65: Land Ecosystem Accounts Project | G65: - | H65: General - no source
... A79: Water quality change | B79: Change in the physical, chemical and biological characteristics of water. | C79: Change in the physical, chemical and biological characteristics of water and the measure of its condition relative to the requirements for one or more biotic species and/or to any human need or purpose. | E79: Part of the definition for this term is re-used from 'Glossary of Terms', Australia and New Zealand Guidelines for fresh and marine water quality, Australian Goverment Initiative. © Commonwealth of Australia | F79: Commonwealth of Australia | G79: - | H79: https://www.waterquality.gov.au/anz-guidelines/resources/glossary
A80: Wave action | B80: Disturbance on the surface of a liquid body. | C80: Disturbance on the surface of a liquid body, as the sea or a lake, in the form of a moving ridge or swell that impacts on the structure of land elements. | E80: Part of the definition for this term is re-used from 'Wave', Dictionary.com, Copyright © 2021 Dictionary.com, LLC | F80: Dictionary.com | G80: -

Sheet Pressures
A1: Pressure | B1: Definition short | C1: Definition | D1: Copyright | E1: Authority | F1: Authority citation
